{
"meta":{"test_sets":[],"test_metrics":[],"learn_metrics":[{"best_value":"Min","name":"RMSE"}],"launch_mode":"Train","parameters":"","iteration_count":1000,"learn_sets":["learn"],"name":"experiment"},
"iterations":[
{"learn":[489673.173],"iteration":0,"passed_time":0.007549646293,"remaining_time":7.542096647},
{"learn":[461952.0818],"iteration":1,"passed_time":0.01218993446,"remaining_time":6.082777294},
{"learn":[436258.8726],"iteration":2,"passed_time":0.01681045805,"remaining_time":5.586675558},
{"learn":[410912.6185],"iteration":3,"passed_time":0.02085746952,"remaining_time":5.193509911},
{"learn":[387934.2745],"iteration":4,"passed_time":0.02563901592,"remaining_time":5.102164168},
{"learn":[366400.7412],"iteration":5,"passed_time":0.03004073525,"remaining_time":4.976748474},
{"learn":[346944.3825],"iteration":6,"passed_time":0.03419604771,"remaining_time":4.850953625},
{"learn":[329351.5932],"iteration":7,"passed_time":0.03874069811,"remaining_time":4.803846566},
{"learn":[311927.3984],"iteration":8,"passed_time":0.04295012189,"remaining_time":4.729285643},
{"learn":[295251.8406],"iteration":9,"passed_time":0.04560559843,"remaining_time":4.514954245},
{"learn":[279905.1652],"iteration":10,"passed_time":0.04821877518,"remaining_time":4.335306241},
{"learn":[264863.835],"iteration":11,"passed_time":0.05211948769,"remaining_time":4.291171153},
{"learn":[251856.9185],"iteration":12,"passed_time":0.05597310524,"remaining_time":4.249650375},
{"learn":[240399.4581],"iteration":13,"passed_time":0.05861900256,"remaining_time":4.128452609},
{"learn":[228395.8029],"iteration":14,"passed_time":0.06163193373,"remaining_time":4.047163648},
{"learn":[217415.1628],"iteration":15,"passed_time":0.0654158683,"remaining_time":4.023075901},
{"learn":[207325.6194],"iteration":16,"passed_time":0.06840791986,"remaining_time":3.955587366},
{"learn":[197436.8372],"iteration":17,"passed_time":0.07274352801,"remaining_time":3.968563584},
{"learn":[189083.9558],"iteration":18,"passed_time":0.07641330696,"remaining_time":3.945339691},
{"learn":[180765.6625],"iteration":19,"passed_time":0.08037995009,"remaining_time":3.938617554},
{"learn":[172767.4056],"iteration":20,"passed_time":0.08411458073,"remaining_time":3.921341645},
{"learn":[165641.6233],"iteration":21,"passed_time":0.08781119339,"remaining_time":3.903606688},
{"learn":[158990.8179],"iteration":22,"passed_time":0.09141585563,"remaining_time":3.883186563},
{"learn":[152738.5299],"iteration":23,"passed_time":0.09461128868,"remaining_time":3.84752574},
{"learn":[147023.8136],"iteration":24,"passed_time":0.09808576641,"remaining_time":3.82534489},
{"learn":[141502.231],"iteration":25,"passed_time":0.1009999319,"remaining_time":3.783612835},
{"learn":[136187.1619],"iteration":26,"passed_time":0.1043747718,"remaining_time":3.761357516},
{"learn":[131653.6417],"iteration":27,"passed_time":0.108143748,"remaining_time":3.754132968},
{"learn":[127314.8583],"iteration":28,"passed_time":0.1114676455,"remaining_time":3.73224427},
{"learn":[123192.2544],"iteration":29,"passed_time":0.1161329401,"remaining_time":3.754965064},
{"learn":[119552.2885],"iteration":30,"passed_time":0.1210497707,"remaining_time":3.783781541},
{"learn":[116089.2405],"iteration":31,"passed_time":0.1247237164,"remaining_time":3.772892422},
{"learn":[112836.0886],"iteration":32,"passed_time":0.1284100782,"remaining_time":3.762804412},
{"learn":[109406.7648],"iteration":33,"passed_time":0.1310075833,"remaining_time":3.72215663},
{"learn":[106413.9472],"iteration":34,"passed_time":0.134577296,"remaining_time":3.710488303},
{"learn":[103760.0721],"iteration":35,"passed_time":0.1374816611,"remaining_time":3.68145337},
{"learn":[101167.6024],"iteration":36,"passed_time":0.1414566701,"remaining_time":3.681696576},
{"learn":[98833.50054],"iteration":37,"passed_time":0.1451607075,"remaining_time":3.67485791},
{"learn":[96912.67921],"iteration":38,"passed_time":0.1488985121,"remaining_time":3.669012055},
{"learn":[94549.08182],"iteration":39,"passed_time":0.1520907062,"remaining_time":3.650176948},
{"learn":[92349.33305],"iteration":40,"passed_time":0.1557037459,"remaining_time":3.641948594},
{"learn":[90367.9013],"iteration":41,"passed_time":0.1593998013,"remaining_time":3.635833564},
{"learn":[88475.3226],"iteration":42,"passed_time":0.1634337513,"remaining_time":3.637351162},
{"learn":[86958.01148],"iteration":43,"passed_time":0.1673416151,"remaining_time":3.63587691},
{"learn":[85601.53384],"iteration":44,"passed_time":0.1711181567,"remaining_time":3.631507547},
{"learn":[83997.42536],"iteration":45,"passed_time":0.175123205,"remaining_time":3.631902991},
{"learn":[82406.35025],"iteration":46,"passed_time":0.1788097429,"remaining_time":3.625652872},
{"learn":[81173.14204],"iteration":47,"passed_time":0.1828836442,"remaining_time":3.627192276},
{"learn":[79568.84501],"iteration":48,"passed_time":0.1895096618,"remaining_time":3.678034456},
{"learn":[78307.3174],"iteration":49,"passed_time":0.1921314433,"remaining_time":3.650497422},
{"learn":[77040.03381],"iteration":50,"passed_time":0.1949218673,"remaining_time":3.62707553},
{"learn":[75958.28839],"iteration":51,"passed_time":0.1988426888,"remaining_time":3.625055173},
{"learn":[75050.57413],"iteration":52,"passed_time":0.2036585969,"remaining_time":3.63895644},
{"learn":[74073.76388],"iteration":53,"passed_time":0.2083354408,"remaining_time":3.649728278},
{"learn":[73280.37388],"iteration":54,"passed_time":0.2130896418,"remaining_time":3.661267482},
{"learn":[72310.96221],"iteration":55,"passed_time":0.2160157283,"remaining_time":3.641407992},
{"learn":[71319.28943],"iteration":56,"passed_time":0.2199700916,"remaining_time":3.639154322},
{"learn":[70389.91605],"iteration":57,"passed_time":0.2226207902,"remaining_time":3.615668696},
{"learn":[69449.81756],"iteration":58,"passed_time":0.2255412748,"remaining_time":3.597192197},
{"learn":[68712.75524],"iteration":59,"passed_time":0.2280939861,"remaining_time":3.573472449},
{"learn":[67933.74445],"iteration":60,"passed_time":0.2312038362,"remaining_time":3.559022987},
{"learn":[67156.29677],"iteration":61,"passed_time":0.2341565342,"remaining_time":3.542561759},
{"learn":[66527.9192],"iteration":62,"passed_time":0.2368282729,"remaining_time":3.522350663},
{"learn":[66005.19942],"iteration":63,"passed_time":0.2393908035,"remaining_time":3.501090501},
{"learn":[65461.24053],"iteration":64,"passed_time":0.2420395737,"remaining_time":3.481646175},
{"learn":[64863.99925],"iteration":65,"passed_time":0.244813191,"remaining_time":3.464477582},
{"learn":[64145.22807],"iteration":66,"passed_time":0.2474701598,"remaining_time":3.446114315},
{"learn":[63514.54238],"iteration":67,"passed_time":0.2500994055,"remaining_time":3.427833028},
{"learn":[63085.13921],"iteration":68,"passed_time":0.2527297561,"remaining_time":3.410020333},
{"learn":[62659.37724],"iteration":69,"passed_time":0.2554714179,"remaining_time":3.394120266},
{"learn":[62363.28312],"iteration":70,"passed_time":0.2582364382,"remaining_time":3.378896495},
{"learn":[61780.4246],"iteration":71,"passed_time":0.2607097157,"remaining_time":3.360258558},
{"learn":[61345.40691],"iteration":72,"passed_time":0.2635247283,"remaining_time":3.346403057},
{"learn":[61029.81355],"iteration":73,"passed_time":0.2662514551,"remaining_time":3.331741182},
{"learn":[60806.546],"iteration":74,"passed_time":0.268942794,"remaining_time":3.316961126},
{"learn":[60347.26857],"iteration":75,"passed_time":0.2715713407,"remaining_time":3.301735774},
{"learn":[59806.90595],"iteration":76,"passed_time":0.2741138284,"remaining_time":3.285806021},
{"learn":[59595.28204],"iteration":77,"passed_time":0.2769895059,"remaining_time":3.274158005},
{"learn":[59152.76884],"iteration":78,"passed_time":0.2810118482,"remaining_time":3.276100154},
{"learn":[58920.00855],"iteration":79,"passed_time":0.2846172832,"remaining_time":3.273098757},
{"learn":[58724.5861],"iteration":80,"passed_time":0.2876076786,"remaining_time":3.263104403},
{"learn":[58436.43488],"iteration":81,"passed_time":0.2902127367,"remaining_time":3.24896698},
{"learn":[58013.56075],"iteration":82,"passed_time":0.2928877695,"remaining_time":3.235880538},
{"learn":[57854.62194],"iteration":83,"passed_time":0.2956343414,"remaining_time":3.223822104},
{"learn":[57592.7235],"iteration":84,"passed_time":0.298232666,"remaining_time":3.210386934},
{"learn":[57305.06072],"iteration":85,"passed_time":0.3008814051,"remaining_time":3.197739584},
{"learn":[56973.07099],"iteration":86,"passed_time":0.3035176182,"remaining_time":3.185190637},
{"learn":[56792.42859],"iteration":87,"passed_time":0.3062349852,"remaining_time":3.173708029},
{"learn":[56699.95123],"iteration":88,"passed_time":0.3090202468,"remaining_time":3.163117358},
{"learn":[56487.58288],"iteration":89,"passed_time":0.3115975834,"remaining_time":3.150597788},
{"learn":[55990.93075],"iteration":90,"passed_time":0.3142198533,"remaining_time":3.138745567},
{"learn":[55801.12893],"iteration":91,"passed_time":0.3170511843,"remaining_time":3.12915734},
{"learn":[55677.27264],"iteration":92,"passed_time":0.3197738609,"remaining_time":3.118654751},
{"learn":[55548.40529],"iteration":93,"passed_time":0.3225888063,"remaining_time":3.109207006},
{"learn":[55439.26605],"iteration":94,"passed_time":0.3254875424,"remaining_time":3.100697115},
{"learn":[55190.25741],"iteration":95,"passed_time":0.3289372348,"remaining_time":3.097492295},
{"learn":[54744.17261],"iteration":96,"passed_time":0.3316908109,"remaining_time":3.087802085},
{"learn":[54592.28727],"iteration":97,"passed_time":0.334617298,"remaining_time":3.079844926},
{"learn":[54095.92747],"iteration":98,"passed_time":0.3371770329,"remaining_time":3.068651582},
{"learn":[53941.02528],"iteration":99,"passed_time":0.3397841827,"remaining_time":3.058057644},
{"learn":[53819.1926],"iteration":100,"passed_time":0.3425500003,"remaining_time":3.049034161},
{"learn":[53549.45596],"iteration":101,"passed_time":0.3452367479,"remaining_time":3.039437252},
{"learn":[53445.32194],"iteration":102,"passed_time":0.3485670701,"remaining_time":3.035579242},
{"learn":[53349.65299],"iteration":103,"passed_time":0.3537699172,"remaining_time":3.047863902},
{"learn":[53091.61421],"iteration":104,"passed_time":0.357719922,"remaining_time":3.049136478},
{"learn":[52979.70177],"iteration":105,"passed_time":0.3603895996,"remaining_time":3.039512284},
{"learn":[52716.38729],"iteration":106,"passed_time":0.3631360388,"remaining_time":3.030658716},
{"learn":[52484.3542],"iteration":107,"passed_time":0.3657507122,"remaining_time":3.020829957},
{"learn":[52226.13163],"iteration":108,"passed_time":0.3683442838,"remaining_time":3.010961073},
{"learn":[51953.37139],"iteration":109,"passed_time":0.3713712949,"remaining_time":3.004731386},
{"learn":[51817.39019],"iteration":110,"passed_time":0.3749948551,"remaining_time":3.003337173},
{"learn":[51779.86426],"iteration":111,"passed_time":0.3777497623,"remaining_time":2.995015972},
{"learn":[51455.75327],"iteration":112,"passed_time":0.3807080704,"remaining_time":2.988389898},
{"learn":[51328.53591],"iteration":113,"passed_time":0.3833660121,"remaining_time":2.979493743},
{"learn":[51069.23489],"iteration":114,"passed_time":0.3862472759,"remaining_time":2.972424688},
{"learn":[50808.05992],"iteration":115,"passed_time":0.3902056865,"remaining_time":2.973636439},
{"learn":[50336.15595],"iteration":116,"passed_time":0.3939086188,"remaining_time":2.972831713},
{"learn":[50301.00116],"iteration":117,"passed_time":0.3974449709,"remaining_time":2.970732749},
{"learn":[50246.75881],"iteration":118,"passed_time":0.3999768221,"remaining_time":2.961172943},
{"learn":[50160.43944],"iteration":119,"passed_time":0.4029290017,"remaining_time":2.954812679},
{"learn":[49887.34201],"iteration":120,"passed_time":0.4056134665,"remaining_time":2.946563942},
{"learn":[49815.42263],"iteration":121,"passed_time":0.4087028664,"remaining_time":2.941320629},
{"learn":[49741.20131],"iteration":122,"passed_time":0.4116142613,"remaining_time":2.934843147},
{"learn":[49548.58558],"iteration":123,"passed_time":0.4144327451,"remaining_time":2.927766812},
{"learn":[49326.9003],"iteration":124,"passed_time":0.417108983,"remaining_time":2.919762881},
{"learn":[49056.8961],"iteration":125,"passed_time":0.4198461473,"remaining_time":2.912266133},
{"learn":[48528.24228],"iteration":126,"passed_time":0.4232669232,"remaining_time":2.909543496},
{"learn":[48509.42087],"iteration":127,"passed_time":0.4276783534,"remaining_time":2.913558783},
{"learn":[48365.76733],"iteration":128,"passed_time":0.4303693523,"remaining_time":2.905827177},
{"learn":[48130.41317],"iteration":129,"passed_time":0.4335035799,"remaining_time":2.901139343},
{"learn":[48027.73678],"iteration":130,"passed_time":0.4361055596,"remaining_time":2.892944514},
{"learn":[47869.14508],"iteration":131,"passed_time":0.4385895552,"remaining_time":2.88405859},
{"learn":[47764.69336],"iteration":132,"passed_time":0.4413079778,"remaining_time":2.876797119},
{"learn":[47298.46518],"iteration":133,"passed_time":0.4438148992,"remaining_time":2.868236587},
{"learn":[47245.2996],"iteration":134,"passed_time":0.4466992143,"remaining_time":2.862183854},
{"learn":[46818.06685],"iteration":135,"passed_time":0.4493993173,"remaining_time":2.855007428},
{"learn":[46724.36741],"iteration":136,"passed_time":0.4523045687,"remaining_time":2.849188633},
{"learn":[46312.96155],"iteration":137,"passed_time":0.456494374,"remaining_time":2.851435872},
{"learn":[46102.42331],"iteration":138,"passed_time":0.460665777,"remaining_time":2.853476504},
{"learn":[46005.01032],"iteration":139,"passed_time":0.4642012707,"remaining_time":2.851522092},
{"learn":[45851.53217],"iteration":140,"passed_time":0.4688208582,"remaining_time":2.856149767},
{"learn":[45462.45591],"iteration":141,"passed_time":0.4746584501,"remaining_time":2.868006691},
{"learn":[45378.88268],"iteration":142,"passed_time":0.487553774,"remaining_time":2.921913177},
{"learn":[45312.27394],"iteration":143,"passed_time":0.4967929417,"remaining_time":2.953158042},
{"learn":[45116.25833],"iteration":144,"passed_time":0.5095943162,"remaining_time":3.004849244},
{"learn":[44664.12785],"iteration":145,"passed_time":0.5170164998,"remaining_time":3.024192403},
{"learn":[44300.2142],"iteration":146,"passed_time":0.5215080528,"remaining_time":3.026165776},
{"learn":[44104.12015],"iteration":147,"passed_time":0.5289308647,"remaining_time":3.044926329},
{"learn":[43935.72357],"iteration":148,"passed_time":0.5341512691,"remaining_time":3.050756577},
{"learn":[43864.42894],"iteration":149,"passed_time":0.5424958202,"remaining_time":3.074142981},
{"learn":[43649.33485],"iteration":150,"passed_time":0.5592670246,"remaining_time":3.144488105},
{"learn":[43551.0044],"iteration":151,"passed_time":0.5718887213,"remaining_time":3.190537077},
{"learn":[43383.7404],"iteration":152,"passed_time":0.5764622905,"remaining_time":3.191265098},
{"learn":[43110.90943],"iteration":153,"passed_time":0.5802456211,"remaining_time":3.187583087},
{"learn":[43007.73482],"iteration":154,"passed_time":0.5848669703,"remaining_time":3.188468322},
{"learn":[42983.48132],"iteration":155,"passed_time":0.587608222,"remaining_time":3.17911115},
{"learn":[42930.35159],"iteration":156,"passed_time":0.5903428041,"remaining_time":3.169802445},
{"learn":[42634.0916],"iteration":157,"passed_time":0.5946310562,"remaining_time":3.168856641},
{"learn":[42432.88956],"iteration":158,"passed_time":0.6030715906,"remaining_time":3.189831495},
{"learn":[42232.90738],"iteration":159,"passed_time":0.60802143,"remaining_time":3.192112508},
{"learn":[42150.35342],"iteration":160,"passed_time":0.6118144449,"remaining_time":3.188275275},
{"learn":[41628.11664],"iteration":161,"passed_time":0.6198066482,"remaining_time":3.206160316},
{"learn":[41438.88794],"iteration":162,"passed_time":0.6234398315,"remaining_time":3.201344411},
{"learn":[41263.76255],"iteration":163,"passed_time":0.6265466548,"remaining_time":3.193859777},
{"learn":[40778.1098],"iteration":164,"passed_time":0.6293407378,"remaining_time":3.184845552},
{"learn":[40702.92014],"iteration":165,"passed_time":0.631962766,"remaining_time":3.175041848},
{"learn":[40411.95747],"iteration":166,"passed_time":0.6348810333,"remaining_time":3.166801801},
{"learn":[40008.17958],"iteration":167,"passed_time":0.6377823328,"remaining_time":3.158541077},
{"learn":[39622.88255],"iteration":168,"passed_time":0.6406760948,"remaining_time":3.150306715},
{"learn":[39415.47557],"iteration":169,"passed_time":0.6451762504,"remaining_time":3.149978164},
{"learn":[39393.5902],"iteration":170,"passed_time":0.6483144109,"remaining_time":3.142997933},
{"learn":[39288.72681],"iteration":171,"passed_time":0.6543110233,"remaining_time":3.149822833},
{"learn":[39246.17945],"iteration":172,"passed_time":0.6572505975,"remaining_time":3.141885804},
{"learn":[39192.35107],"iteration":173,"passed_time":0.65991685,"remaining_time":3.132708725},
{"learn":[38767.831],"iteration":174,"passed_time":0.6628118626,"remaining_time":3.124684495},
{"learn":[38679.5758],"iteration":175,"passed_time":0.6654915655,"remaining_time":3.115710511},
{"learn":[38323.97356],"iteration":176,"passed_time":0.6686812717,"remaining_time":3.109179021},
{"learn":[38231.635],"iteration":177,"passed_time":0.6715337618,"remaining_time":3.101127821},
{"learn":[37940.31951],"iteration":178,"passed_time":0.6744651957,"remaining_time":3.093496791},
{"learn":[37881.30745],"iteration":179,"passed_time":0.6782440101,"remaining_time":3.089778268},
{"learn":[37751.92348],"iteration":180,"passed_time":0.6816054055,"remaining_time":3.084170316},
{"learn":[37703.17096],"iteration":181,"passed_time":0.6840672515,"remaining_time":3.07454402},
{"learn":[37675.50162],"iteration":182,"passed_time":0.6876623606,"remaining_time":3.070055457},
{"learn":[37639.29455],"iteration":183,"passed_time":0.6902586051,"remaining_time":3.061146857},
{"learn":[37372.79457],"iteration":184,"passed_time":0.6927574818,"remaining_time":3.051877555},
{"learn":[37234.43808],"iteration":185,"passed_time":0.6982685313,"remaining_time":3.055863357},
{"learn":[37116.55386],"iteration":186,"passed_time":0.7009010703,"remaining_time":3.047232996},
{"learn":[36803.63834],"iteration":187,"passed_time":0.7035169561,"remaining_time":3.038594512},
{"learn":[36507.85648],"iteration":188,"passed_time":0.7071430029,"remaining_time":3.034354367},
{"learn":[36211.40133],"iteration":189,"passed_time":0.7097791655,"remaining_time":3.025900653},
{"learn":[36188.2316],"iteration":190,"passed_time":0.7123365792,"remaining_time":3.017174307},
{"learn":[36140.61376],"iteration":191,"passed_time":0.7147860219,"remaining_time":3.008057842},
{"learn":[35866.94065],"iteration":192,"passed_time":0.7173558972,"remaining_time":2.999514036},
{"learn":[35482.72325],"iteration":193,"passed_time":0.7224835106,"remaining_time":3.001658296},
{"learn":[35120.35281],"iteration":194,"passed_time":0.7254673246,"remaining_time":2.99487793},
{"learn":[35079.52524],"iteration":195,"passed_time":0.7312877876,"remaining_time":2.999772353},
{"learn":[34737.9431],"iteration":196,"passed_time":0.7343752519,"remaining_time":2.993417905},
{"learn":[34694.09395],"iteration":197,"passed_time":0.7384523072,"remaining_time":2.9911048},
{"learn":[34409.10212],"iteration":198,"passed_time":0.7414410342,"remaining_time":2.984393308},
{"learn":[34371.81801],"iteration":199,"passed_time":0.747799188,"remaining_time":2.991196752},
{"learn":[34343.45837],"iteration":200,"passed_time":0.753730616,"remaining_time":2.996172946},
{"learn":[34023.19356],"iteration":201,"passed_time":0.7576363415,"remaining_time":2.993038616},
{"learn":[33972.48168],"iteration":202,"passed_time":0.7635685916,"remaining_time":2.997853042},
{"learn":[33670.72089],"iteration":203,"passed_time":0.7668883185,"remaining_time":2.992368145},
{"learn":[33635.99966],"iteration":204,"passed_time":0.7709444852,"remaining_time":2.989760321},
{"learn":[33612.17864],"iteration":205,"passed_time":0.7737409745,"remaining_time":2.982283173},
{"learn":[33598.42554],"iteration":206,"passed_time":0.7775531928,"remaining_time":2.978742425},
{"learn":[33529.40726],"iteration":207,"passed_time":0.7800910892,"remaining_time":2.970346839},
{"learn":[33317.92206],"iteration":208,"passed_time":0.7828677688,"remaining_time":2.962911029},
{"learn":[33053.08589],"iteration":209,"passed_time":0.7856734633,"remaining_time":2.955628743},
{"learn":[32799.43666],"iteration":210,"passed_time":0.7882916864,"remaining_time":2.94768787},
{"learn":[32525.59227],"iteration":211,"passed_time":0.7952986377,"remaining_time":2.956110031},
{"learn":[32494.36847],"iteration":212,"passed_time":0.8079004965,"remaining_time":2.985059581},
{"learn":[32303.12698],"iteration":213,"passed_time":0.8123930184,"remaining_time":2.98383604},
{"learn":[31997.74554],"iteration":214,"passed_time":0.8158378012,"remaining_time":2.978756623},
{"learn":[31967.90093],"iteration":215,"passed_time":0.8184038402,"remaining_time":2.970502827},
{"learn":[31945.51642],"iteration":216,"passed_time":0.8209441189,"remaining_time":2.962208503},
{"learn":[31932.88394],"iteration":217,"passed_time":0.823901177,"remaining_time":2.95546202},
{"learn":[31655.67501],"iteration":218,"passed_time":0.8263165613,"remaining_time":2.946818422},
{"learn":[31634.33378],"iteration":219,"passed_time":0.8288107211,"remaining_time":2.938510739},
{"learn":[31619.15326],"iteration":220,"passed_time":0.8312715265,"remaining_time":2.930138096},
{"learn":[31593.7094],"iteration":221,"passed_time":0.8337788329,"remaining_time":2.921981676},
{"learn":[31573.07817],"iteration":222,"passed_time":0.8366855587,"remaining_time":2.915267619},
{"learn":[31345.21682],"iteration":223,"passed_time":0.8397029712,"remaining_time":2.908971007},
{"learn":[31087.55377],"iteration":224,"passed_time":0.8434029284,"remaining_time":2.905054531},
{"learn":[31044.81521],"iteration":225,"passed_time":0.8471994717,"remaining_time":2.901470757},
{"learn":[30797.63756],"iteration":226,"passed_time":0.8513495423,"remaining_time":2.89908897},
{"learn":[30701.14854],"iteration":227,"passed_time":0.8554902765,"remaining_time":2.896660059},
{"learn":[30678.93042],"iteration":228,"passed_time":0.863176897,"remaining_time":2.906154531},
{"learn":[30647.89071],"iteration":229,"passed_time":0.8681772887,"remaining_time":2.906506575},
{"learn":[30521.31315],"iteration":230,"passed_time":0.8726226424,"remaining_time":2.904964554},
{"learn":[30417.47953],"iteration":231,"passed_time":0.8760387081,"remaining_time":2.899990206},
{"learn":[30394.86772],"iteration":232,"passed_time":0.8791099479,"remaining_time":2.89389412},
{"learn":[30384.59581],"iteration":233,"passed_time":0.8817302694,"remaining_time":2.886347805},
{"learn":[30152.17992],"iteration":234,"passed_time":0.8844867505,"remaining_time":2.879286656},
{"learn":[30129.27844],"iteration":235,"passed_time":0.8870957416,"remaining_time":2.871784519},
{"learn":[30080.40177],"iteration":236,"passed_time":0.8920204063,"remaining_time":2.871778776},
{"learn":[29863.08473],"iteration":237,"passed_time":0.8966641857,"remaining_time":2.870832393},
{"learn":[29786.99029],"iteration":238,"passed_time":0.9054929269,"remaining_time":2.883180407},
{"learn":[29515.95121],"iteration":239,"passed_time":0.9092931253,"remaining_time":2.87942823},
{"learn":[29284.95244],"iteration":240,"passed_time":0.9130798245,"remaining_time":2.87563314},
{"learn":[29093.05275],"iteration":241,"passed_time":0.9168722416,"remaining_time":2.871856029},
{"learn":[28893.89531],"iteration":242,"passed_time":0.9208924943,"remaining_time":2.868788552},
{"learn":[28664.21312],"iteration":243,"passed_time":0.925235885,"remaining_time":2.866714463},
{"learn":[28645.43304],"iteration":244,"passed_time":0.928146377,"remaining_time":2.860206182},
{"learn":[28431.39337],"iteration":245,"passed_time":0.9309140497,"remaining_time":2.853289404},
{"learn":[28380.71134],"iteration":246,"passed_time":0.9337370465,"remaining_time":2.846574883},
{"learn":[28178.46226],"iteration":247,"passed_time":0.9364942893,"remaining_time":2.839692361},
{"learn":[28160.22126],"iteration":248,"passed_time":0.9408281624,"remaining_time":2.837598193},
{"learn":[27949.57096],"iteration":249,"passed_time":0.9447932155,"remaining_time":2.834379647},
{"learn":[27910.26424],"iteration":250,"passed_time":0.9490509498,"remaining_time":2.832028532},
{"learn":[27680.72228],"iteration":251,"passed_time":0.9532272475,"remaining_time":2.82942056},
{"learn":[27664.43068],"iteration":252,"passed_time":0.9580127373,"remaining_time":2.828598873},
{"learn":[27621.04391],"iteration":253,"passed_time":0.9614823238,"remaining_time":2.823881156},
{"learn":[27594.06064],"iteration":254,"passed_time":0.964295778,"remaining_time":2.817256293},
{"learn":[27420.20677],"iteration":255,"passed_time":0.9672752747,"remaining_time":2.811143767},
{"learn":[27403.29089],"iteration":256,"passed_time":0.9707174441,"remaining_time":2.806393233},
{"learn":[27324.90248],"iteration":257,"passed_time":0.9743303433,"remaining_time":2.802143856},
{"learn":[27240.50375],"iteration":258,"passed_time":0.9771690429,"remaining_time":2.795684404},
{"learn":[27182.32077],"iteration":259,"passed_time":0.9796940499,"remaining_time":2.788359988},
{"learn":[27169.46869],"iteration":260,"passed_time":0.9822725621,"remaining_time":2.781223844},
{"learn":[27136.88785],"iteration":261,"passed_time":0.9850117971,"remaining_time":2.774575215},
{"learn":[26972.48222],"iteration":262,"passed_time":0.9890541295,"remaining_time":2.77160796},
{"learn":[26829.25356],"iteration":263,"passed_time":0.9917340253,"remaining_time":2.764834252},
{"learn":[26778.45549],"iteration":264,"passed_time":0.9944470649,"remaining_time":2.758183369},
{"learn":[26590.61182],"iteration":265,"passed_time":0.997098928,"remaining_time":2.751393283},
{"learn":[26505.73121],"iteration":266,"passed_time":0.9996116607,"remaining_time":2.744252237},
{"learn":[26483.23679],"iteration":267,"passed_time":1.00227892,"remaining_time":2.737567796},
{"learn":[26436.12014],"iteration":268,"passed_time":1.00484933,"remaining_time":2.730650037},
{"learn":[26364.22605],"iteration":269,"passed_time":1.007404335,"remaining_time":2.723722833},
{"learn":[26302.56753],"iteration":270,"passed_time":1.009864208,"remaining_time":2.716571984},
{"learn":[26234.72446],"iteration":271,"passed_time":1.012467474,"remaining_time":2.709839417},
{"learn":[26119.49479],"iteration":272,"passed_time":1.01533375,"remaining_time":2.703837497},
{"learn":[26109.95428],"iteration":273,"passed_time":1.017902257,"remaining_time":2.697069483},
{"learn":[26095.30701],"iteration":274,"passed_time":1.0205202,"remaining_time":2.690462346},
{"learn":[26033.45967],"iteration":275,"passed_time":1.023335226,"remaining_time":2.684401101},
{"learn":[25929.85327],"iteration":276,"passed_time":1.025863737,"remaining_time":2.677615459},
{"learn":[25769.92833],"iteration":277,"passed_time":1.028566998,"remaining_time":2.671314291},
{"learn":[25619.08769],"iteration":278,"passed_time":1.031343891,"remaining_time":2.665229196},
{"learn":[25527.03215],"iteration":279,"passed_time":1.034609085,"remaining_time":2.66042336},
{"learn":[25350.83777],"iteration":280,"passed_time":1.037267703,"remaining_time":2.654076437},
{"learn":[25182.98329],"iteration":281,"passed_time":1.039632518,"remaining_time":2.647007616},
{"learn":[25132.51852],"iteration":282,"passed_time":1.042095196,"remaining_time":2.640219985},
{"learn":[24898.80426],"iteration":283,"passed_time":1.044363034,"remaining_time":2.632971593},
{"learn":[24868.97979],"iteration":284,"passed_time":1.046644184,"remaining_time":2.62579155},
{"learn":[24859.22669],"iteration":285,"passed_time":1.048961386,"remaining_time":2.618735767},
{"learn":[24845.95014],"iteration":286,"passed_time":1.051239919,"remaining_time":2.611616941},
{"learn":[24680.44914],"iteration":287,"passed_time":1.053456812,"remaining_time":2.604379341},
{"learn":[24634.50045],"iteration":288,"passed_time":1.055765559,"remaining_time":2.597402465},
{"learn":[24590.70003],"iteration":289,"passed_time":1.05798533,"remaining_time":2.590239945},
{"learn":[24468.15805],"iteration":290,"passed_time":1.06043831,"remaining_time":2.583679595},
{"learn":[24455.48291],"iteration":291,"passed_time":1.062872038,"remaining_time":2.577100695},
{"learn":[24298.05349],"iteration":292,"passed_time":1.065388316,"remaining_time":2.570749281},
{"learn":[24122.17784],"iteration":293,"passed_time":1.0680596,"remaining_time":2.564796183},
{"learn":[24080.8968],"iteration":294,"passed_time":1.070711067,"remaining_time":2.558817974},
{"learn":[24073.94197],"iteration":295,"passed_time":1.073317629,"remaining_time":2.552755443},
{"learn":[24062.09719],"iteration":296,"passed_time":1.075630687,"remaining_time":2.546021457},
{"learn":[24024.63823],"iteration":297,"passed_time":1.077839671,"remaining_time":2.539071976},
{"learn":[24010.25387],"iteration":298,"passed_time":1.080183634,"remaining_time":2.532470661},
{"learn":[23899.70372],"iteration":299,"passed_time":1.082418934,"remaining_time":2.52564418},
{"learn":[23753.71291],"iteration":300,"passed_time":1.084893361,"remaining_time":2.51940352},
{"learn":[23711.70167],"iteration":301,"passed_time":1.087334789,"remaining_time":2.513111533},
{"learn":[23584.71599],"iteration":302,"passed_time":1.090047361,"remaining_time":2.507468682},
{"learn":[23435.70783],"iteration":303,"passed_time":1.093161316,"remaining_time":2.502764067},
{"learn":[23428.03622],"iteration":304,"passed_time":1.09578846,"remaining_time":2.49696059},
{"learn":[23295.04426],"iteration":305,"passed_time":1.098201182,"remaining_time":2.490691569},
{"learn":[23261.65465],"iteration":306,"passed_time":1.100711308,"remaining_time":2.484667546},
{"learn":[23255.36835],"iteration":307,"passed_time":1.10310195,"remaining_time":2.478397887},
{"learn":[23140.34437],"iteration":308,"passed_time":1.105472896,"remaining_time":2.472109292},
{"learn":[23106.97892],"iteration":309,"passed_time":1.107896752,"remaining_time":2.465963738},
{"learn":[23100.39271],"iteration":310,"passed_time":1.110359063,"remaining_time":2.459927314},
{"learn":[23041.5094],"iteration":311,"passed_time":1.112642412,"remaining_time":2.453519164},
{"learn":[22946.22715],"iteration":312,"passed_time":1.114838394,"remaining_time":2.446945612},
{"learn":[22891.36294],"iteration":313,"passed_time":1.120695291,"remaining_time":2.448397993},
{"learn":[22860.51378],"iteration":314,"passed_time":1.123832919,"remaining_time":2.443890632},
{"learn":[22854.8311],"iteration":315,"passed_time":1.126479266,"remaining_time":2.438328538},
{"learn":[22721.13577],"iteration":316,"passed_time":1.129439615,"remaining_time":2.433461378},
{"learn":[22599.77326],"iteration":317,"passed_time":1.132234785,"remaining_time":2.42825196},
{"learn":[22570.39334],"iteration":318,"passed_time":1.135707679,"remaining_time":2.424504482},
{"learn":[22552.6301],"iteration":319,"passed_time":1.138483716,"remaining_time":2.419277896},
{"learn":[22405.35138],"iteration":320,"passed_time":1.140804493,"remaining_time":2.413103586},
{"learn":[22271.14092],"iteration":321,"passed_time":1.143104867,"remaining_time":2.406910248},
{"learn":[22155.35464],"iteration":322,"passed_time":1.14506623,"remaining_time":2.400030457},
{"learn":[22107.54236],"iteration":323,"passed_time":1.146925671,"remaining_time":2.392968375},
{"learn":[22095.78202],"iteration":324,"passed_time":1.148826918,"remaining_time":2.386025138},
{"learn":[21989.91208],"iteration":325,"passed_time":1.151714689,"remaining_time":2.381152455},
{"learn":[21947.831],"iteration":326,"passed_time":1.154005533,"remaining_time":2.375063376},
{"learn":[21941.96824],"iteration":327,"passed_time":1.156411858,"remaining_time":2.369234051},
{"learn":[21897.39856],"iteration":328,"passed_time":1.158397776,"remaining_time":2.362568108},
{"learn":[21846.61919],"iteration":329,"passed_time":1.160362617,"remaining_time":2.355887738},
{"learn":[21716.61529],"iteration":330,"passed_time":1.162441014,"remaining_time":2.349465373},
{"learn":[21697.50138],"iteration":331,"passed_time":1.164803221,"remaining_time":2.343640215},
{"learn":[21569.07168],"iteration":332,"passed_time":1.167463545,"remaining_time":2.338432986},
{"learn":[21545.99011],"iteration":333,"passed_time":1.170553539,"remaining_time":2.334097775},
{"learn":[21499.68943],"iteration":334,"passed_time":1.173143568,"remaining_time":2.32877753},
{"learn":[21487.08676],"iteration":335,"passed_time":1.17507452,"remaining_time":2.322171076},
{"learn":[21440.27601],"iteration":336,"passed_time":1.177315284,"remaining_time":2.316201879},
{"learn":[21430.10163],"iteration":337,"passed_time":1.179419754,"remaining_time":2.309987802},
{"learn":[21400.80688],"iteration":338,"passed_time":1.181460304,"remaining_time":2.303673336},
{"learn":[21357.8743],"iteration":339,"passed_time":1.183494692,"remaining_time":2.297372049},
{"learn":[21313.68152],"iteration":340,"passed_time":1.185560811,"remaining_time":2.291157109},
{"learn":[21251.40423],"iteration":341,"passed_time":1.187666925,"remaining_time":2.285043383},
{"learn":[21214.82347],"iteration":342,"passed_time":1.189704855,"remaining_time":2.27882242},
{"learn":[21204.4691],"iteration":343,"passed_time":1.191788213,"remaining_time":2.272712406},
{"learn":[21158.84415],"iteration":344,"passed_time":1.19390187,"remaining_time":2.266683261},
{"learn":[21133.5125],"iteration":345,"passed_time":1.195840301,"remaining_time":2.260345539},
{"learn":[21127.28217],"iteration":346,"passed_time":1.197868755,"remaining_time":2.254202585},
{"learn":[21088.42362],"iteration":347,"passed_time":1.199860989,"remaining_time":2.248015416},
{"learn":[21001.2685],"iteration":348,"passed_time":1.201861932,"remaining_time":2.241868531},
{"learn":[20991.24892],"iteration":349,"passed_time":1.203758301,"remaining_time":2.23555113},
{"learn":[20946.8882],"iteration":350,"passed_time":1.205836746,"remaining_time":2.229595579},
{"learn":[20942.22653],"iteration":351,"passed_time":1.207916569,"remaining_time":2.223664593},
{"learn":[20927.92741],"iteration":352,"passed_time":1.209991272,"remaining_time":2.217746042},
{"learn":[20922.40027],"iteration":353,"passed_time":1.211987479,"remaining_time":2.211705964},
{"learn":[20911.65036],"iteration":354,"passed_time":1.213860687,"remaining_time":2.205465192},
{"learn":[20875.72593],"iteration":355,"passed_time":1.215744999,"remaining_time":2.199269044},
{"learn":[20840.52172],"iteration":356,"passed_time":1.217640879,"remaining_time":2.193117885},
{"learn":[20808.01345],"iteration":357,"passed_time":1.219502722,"remaining_time":2.186929462},
{"learn":[20802.94343],"iteration":358,"passed_time":1.221532999,"remaining_time":2.181065885},
{"learn":[20722.15323],"iteration":359,"passed_time":1.223451858,"remaining_time":2.175025525},
{"learn":[20681.0525],"iteration":360,"passed_time":1.225685015,"remaining_time":2.169564334},
{"learn":[20643.14588],"iteration":361,"passed_time":1.227879454,"remaining_time":2.164052739},
{"learn":[20633.75817],"iteration":362,"passed_time":1.229872923,"remaining_time":2.158206754},
{"learn":[20618.97821],"iteration":363,"passed_time":1.232084668,"remaining_time":2.152763321},
{"learn":[20609.67206],"iteration":364,"passed_time":1.234192638,"remaining_time":2.147157055},
{"learn":[20604.66756],"iteration":365,"passed_time":1.236298864,"remaining_time":2.141566884},
{"learn":[20542.83629],"iteration":366,"passed_time":1.238369601,"remaining_time":2.135934489},
{"learn":[20538.53619],"iteration":367,"passed_time":1.240561652,"remaining_time":2.130529794},
{"learn":[20516.8967],"iteration":368,"passed_time":1.242550573,"remaining_time":2.124795153},
{"learn":[20427.87909],"iteration":369,"passed_time":1.244446919,"remaining_time":2.118923132},
{"learn":[20420.58285],"iteration":370,"passed_time":1.246357437,"remaining_time":2.113096571},
{"learn":[20407.64186],"iteration":371,"passed_time":1.248237018,"remaining_time":2.107238837},
{"learn":[20375.08803],"iteration":372,"passed_time":1.250079237,"remaining_time":2.101339628},
{"learn":[20313.28279],"iteration":373,"passed_time":1.252268233,"remaining_time":2.096042551},
{"learn":[20237.55673],"iteration":374,"passed_time":1.254338578,"remaining_time":2.090564296},
{"learn":[20156.41913],"iteration":375,"passed_time":1.256270093,"remaining_time":2.084873772},
{"learn":[20051.73039],"iteration":376,"passed_time":1.258407229,"remaining_time":2.079542981},
{"learn":[19972.87215],"iteration":377,"passed_time":1.260294907,"remaining_time":2.073818603},
{"learn":[19961.20746],"iteration":378,"passed_time":1.262247784,"remaining_time":2.068221304},
{"learn":[19910.6054],"iteration":379,"passed_time":1.264186579,"remaining_time":2.062620208},
{"learn":[19904.02057],"iteration":380,"passed_time":1.266285039,"remaining_time":2.057297741},
{"learn":[19890.7153],"iteration":381,"passed_time":1.268318912,"remaining_time":2.051887663},
{"learn":[19795.02154],"iteration":382,"passed_time":1.270479153,"remaining_time":2.046698791},
{"learn":[19758.30828],"iteration":383,"passed_time":1.272797831,"remaining_time":2.041779854},
{"learn":[19664.57563],"iteration":384,"passed_time":1.275295054,"remaining_time":2.037159632},
{"learn":[19626.83689],"iteration":385,"passed_time":1.277622264,"remaining_time":2.032279974},
{"learn":[19619.39903],"iteration":386,"passed_time":1.279818805,"remaining_time":2.027206531},
{"learn":[19530.33846],"iteration":387,"passed_time":1.281837729,"remaining_time":2.021867759},
{"learn":[19467.84081],"iteration":388,"passed_time":1.283803998,"remaining_time":2.016463349},
{"learn":[19432.27635],"iteration":389,"passed_time":1.285670959,"remaining_time":2.010921244},
{"learn":[19426.72322],"iteration":390,"passed_time":1.287666685,"remaining_time":2.005598494},
{"learn":[19418.66898],"iteration":391,"passed_time":1.289744651,"remaining_time":2.000420276},
{"learn":[19385.05453],"iteration":392,"passed_time":1.29191165,"remaining_time":1.995395347},
{"learn":[19302.33669],"iteration":393,"passed_time":1.294073168,"remaining_time":1.990376496},
{"learn":[19271.49481],"iteration":394,"passed_time":1.295931213,"remaining_time":1.9849073},
{"learn":[19264.73681],"iteration":395,"passed_time":1.298284354,"remaining_time":1.980211489},
{"learn":[19251.53268],"iteration":396,"passed_time":1.300483456,"remaining_time":1.975293511},
{"learn":[19201.32296],"iteration":397,"passed_time":1.303744439,"remaining_time":1.971995357},
{"learn":[19170.61012],"iteration":398,"passed_time":1.307670202,"remaining_time":1.969698725},
{"learn":[19155.82967],"iteration":399,"passed_time":1.311212057,"remaining_time":1.966818086},
{"learn":[19150.18754],"iteration":400,"passed_time":1.315054626,"remaining_time":1.964383344},
{"learn":[19146.05155],"iteration":401,"passed_time":1.319129073,"remaining_time":1.962286531},
{"learn":[19090.80372],"iteration":402,"passed_time":1.323566298,"remaining_time":1.960717319},
{"learn":[19080.54463],"iteration":403,"passed_time":1.32714024,"remaining_time":1.957860354},
{"learn":[19023.97936],"iteration":404,"passed_time":1.330328155,"remaining_time":1.954432722},
{"learn":[18994.65166],"iteration":405,"passed_time":1.333651398,"remaining_time":1.951204262},
{"learn":[18962.72898],"iteration":406,"passed_time":1.33583325,"remaining_time":1.946312327},
{"learn":[18906.23615],"iteration":407,"passed_time":1.338122589,"remaining_time":1.941589639},
{"learn":[18887.48556],"iteration":408,"passed_time":1.341390885,"remaining_time":1.938293431},
{"learn":[18869.58676],"iteration":409,"passed_time":1.344027388,"remaining_time":1.934088192},
{"learn":[18862.94121],"iteration":410,"passed_time":1.346857138,"remaining_time":1.930167528},
{"learn":[18835.44646],"iteration":411,"passed_time":1.351251942,"remaining_time":1.928485782},
{"learn":[18831.35966],"iteration":412,"passed_time":1.355642711,"remaining_time":1.92678516},
{"learn":[18826.55478],"iteration":413,"passed_time":1.359059713,"remaining_time":1.923693216},
{"learn":[18753.64646],"iteration":414,"passed_time":1.361982633,"remaining_time":1.91990323},
{"learn":[18705.87431],"iteration":415,"passed_time":1.364864425,"remaining_time":1.916059673},
{"learn":[18689.11337],"iteration":416,"passed_time":1.367727533,"remaining_time":1.912194609},
{"learn":[18587.88042],"iteration":417,"passed_time":1.370766444,"remaining_time":1.908579116},
{"learn":[18517.4035],"iteration":418,"passed_time":1.375001977,"remaining_time":1.906625653},
{"learn":[18478.51795],"iteration":419,"passed_time":1.379325435,"remaining_time":1.904782744},
{"learn":[18473.85191],"iteration":420,"passed_time":1.383817152,"remaining_time":1.903159456},
{"learn":[18415.79928],"iteration":421,"passed_time":1.38823448,"remaining_time":1.901420686},
{"learn":[18400.60623],"iteration":422,"passed_time":1.393376278,"remaining_time":1.900657477},
{"learn":[18394.93756],"iteration":423,"passed_time":1.398195799,"remaining_time":1.899435803},
{"learn":[18389.91069],"iteration":424,"passed_time":1.402975719,"remaining_time":1.898143619},
{"learn":[18353.21528],"iteration":425,"passed_time":1.407047088,"remaining_time":1.895880348},
{"learn":[18338.75893],"iteration":426,"passed_time":1.411316357,"remaining_time":1.893874174},
{"learn":[18324.92833],"iteration":427,"passed_time":1.416085396,"remaining_time":1.892525342},
{"learn":[18318.92133],"iteration":428,"passed_time":1.426217303,"remaining_time":1.898298555},
{"learn":[18309.74615],"iteration":429,"passed_time":1.430647145,"remaining_time":1.896439239},
{"learn":[18247.74863],"iteration":430,"passed_time":1.436370829,"remaining_time":1.896276105},
{"learn":[18195.45578],"iteration":431,"passed_time":1.440481559,"remaining_time":1.893966495},
{"learn":[18191.04714],"iteration":432,"passed_time":1.444953225,"remaining_time":1.892121198},
{"learn":[18182.85404],"iteration":433,"passed_time":1.449288319,"remaining_time":1.890085688},
{"learn":[18171.29867],"iteration":434,"passed_time":1.453370196,"remaining_time":1.887710715},
{"learn":[18090.10629],"iteration":435,"passed_time":1.456944253,"remaining_time":1.884671006},
{"learn":[18025.59563],"iteration":436,"passed_time":1.461078053,"remaining_time":1.882349986},
{"learn":[18021.17413],"iteration":437,"passed_time":1.465235904,"remaining_time":1.880051547},
{"learn":[18006.05238],"iteration":438,"passed_time":1.469958602,"remaining_time":1.87846646},
{"learn":[17998.67437],"iteration":439,"passed_time":1.475600324,"remaining_time":1.878036775},
{"learn":[17985.52979],"iteration":440,"passed_time":1.491685864,"remaining_time":1.890821764},
{"learn":[17894.27546],"iteration":441,"passed_time":1.496497687,"remaining_time":1.889243687},
{"learn":[17815.97711],"iteration":442,"passed_time":1.501738939,"remaining_time":1.888190946},
{"learn":[17740.9124],"iteration":443,"passed_time":1.506250453,"remaining_time":1.886205522},
{"learn":[17686.09222],"iteration":444,"passed_time":1.510587286,"remaining_time":1.883990885},
{"learn":[17679.63751],"iteration":445,"passed_time":1.52643087,"remaining_time":1.89605987},
{"learn":[17649.61245],"iteration":446,"passed_time":1.532683602,"remaining_time":1.896138774},
{"learn":[17617.82915],"iteration":447,"passed_time":1.538490728,"remaining_time":1.895640361},
{"learn":[17582.5386],"iteration":448,"passed_time":1.545017746,"remaining_time":1.896001733},
{"learn":[17578.32376],"iteration":449,"passed_time":1.549308548,"remaining_time":1.893599337},
{"learn":[17537.91055],"iteration":450,"passed_time":1.551791052,"remaining_time":1.888987334},
{"learn":[17533.96099],"iteration":451,"passed_time":1.55492122,"remaining_time":1.885169974},
{"learn":[17488.56545],"iteration":452,"passed_time":1.557753265,"remaining_time":1.880995665},
{"learn":[17479.65985],"iteration":453,"passed_time":1.560702087,"remaining_time":1.876967709},
{"learn":[17451.13197],"iteration":454,"passed_time":1.564824981,"remaining_time":1.874350801},
{"learn":[17406.26226],"iteration":455,"passed_time":1.567670783,"remaining_time":1.870203741},
{"learn":[17374.24939],"iteration":456,"passed_time":1.570413867,"remaining_time":1.865940327},
{"learn":[17370.00487],"iteration":457,"passed_time":1.573429322,"remaining_time":1.862005879},
{"learn":[17318.89035],"iteration":458,"passed_time":1.576531596,"remaining_time":1.858177763},
{"learn":[17312.61767],"iteration":459,"passed_time":1.579399473,"remaining_time":1.854077642},
{"learn":[17301.32452],"iteration":460,"passed_time":1.583313163,"remaining_time":1.851205629},
{"learn":[17293.49757],"iteration":461,"passed_time":1.588011559,"remaining_time":1.849242898},
{"learn":[17257.52262],"iteration":462,"passed_time":1.591960895,"remaining_time":1.846399569},
{"learn":[17253.01628],"iteration":463,"passed_time":1.595350705,"remaining_time":1.842905125},
{"learn":[17232.68441],"iteration":464,"passed_time":1.597964956,"remaining_time":1.83851882},
{"learn":[17174.56891],"iteration":465,"passed_time":1.600885717,"remaining_time":1.834491358},
{"learn":[17170.1355],"iteration":466,"passed_time":1.603756266,"remaining_time":1.830411327},
{"learn":[17144.33122],"iteration":467,"passed_time":1.606360142,"remaining_time":1.826033324},
{"learn":[17092.12236],"iteration":468,"passed_time":1.609593697,"remaining_time":1.822375806},
{"learn":[17061.98892],"iteration":469,"passed_time":1.612538771,"remaining_time":1.818394785},
{"learn":[17009.30159],"iteration":470,"passed_time":1.615388259,"remaining_time":1.814310804},
{"learn":[16958.88838],"iteration":471,"passed_time":1.618114813,"remaining_time":1.810094536},
{"learn":[16941.09344],"iteration":472,"passed_time":1.620616767,"remaining_time":1.805634326},
{"learn":[16926.90254],"iteration":473,"passed_time":1.623214589,"remaining_time":1.801288763},
{"learn":[16903.98692],"iteration":474,"passed_time":1.626289784,"remaining_time":1.797478183},
{"learn":[16882.88755],"iteration":475,"passed_time":1.628935748,"remaining_time":1.793198177},
{"learn":[16828.80789],"iteration":476,"passed_time":1.632360531,"remaining_time":1.789778947},
{"learn":[16823.43926],"iteration":477,"passed_time":1.635082213,"remaining_time":1.785591873},
{"learn":[16773.47854],"iteration":478,"passed_time":1.637903165,"remaining_time":1.781518891},
{"learn":[16737.10138],"iteration":479,"passed_time":1.641316123,"remaining_time":1.778092467},
{"learn":[16731.2544],"iteration":480,"passed_time":1.644258111,"remaining_time":1.77415792},
{"learn":[16726.61076],"iteration":481,"passed_time":1.647049544,"remaining_time":1.770065692},
{"learn":[16662.3673],"iteration":482,"passed_time":1.649986324,"remaining_time":1.766134429},
{"learn":[16640.28929],"iteration":483,"passed_time":1.652555673,"remaining_time":1.761815552},
{"learn":[16622.68055],"iteration":484,"passed_time":1.655066155,"remaining_time":1.757441381},
{"learn":[16614.49772],"iteration":485,"passed_time":1.658582455,"remaining_time":1.754138646},
{"learn":[16577.25697],"iteration":486,"passed_time":1.661848624,"remaining_time":1.750571548},
{"learn":[16566.89522],"iteration":487,"passed_time":1.669359226,"remaining_time":1.75145886},
{"learn":[16535.46582],"iteration":488,"passed_time":1.672390753,"remaining_time":1.747631237},
{"learn":[16467.72624],"iteration":489,"passed_time":1.675586673,"remaining_time":1.743977965},
{"learn":[16410.6726],"iteration":490,"passed_time":1.679170285,"remaining_time":1.740728463},
{"learn":[16401.80547],"iteration":491,"passed_time":1.681833422,"remaining_time":1.736527192},
{"learn":[16360.21216],"iteration":492,"passed_time":1.684472601,"remaining_time":1.732307523},
{"learn":[16306.17228],"iteration":493,"passed_time":1.687011,"remaining_time":1.727991024},
{"learn":[16248.88616],"iteration":494,"passed_time":1.692385387,"remaining_time":1.726574991},
{"learn":[16240.71786],"iteration":495,"passed_time":1.696520843,"remaining_time":1.723884082},
{"learn":[16236.90459],"iteration":496,"passed_time":1.700596397,"remaining_time":1.721126736},
{"learn":[16191.16396],"iteration":497,"passed_time":1.703277208,"remaining_time":1.716958149},
{"learn":[16176.67802],"iteration":498,"passed_time":1.70651611,"remaining_time":1.713355854},
{"learn":[16171.62569],"iteration":499,"passed_time":1.7098753,"remaining_time":1.7098753},
{"learn":[16164.10396],"iteration":500,"passed_time":1.713021205,"remaining_time":1.706182797},
{"learn":[16111.03358],"iteration":501,"passed_time":1.715891311,"remaining_time":1.70221887},
{"learn":[16070.04984],"iteration":502,"passed_time":1.719230992,"remaining_time":1.698723267},
{"learn":[16027.53255],"iteration":503,"passed_time":1.723407293,"remaining_time":1.696051622},
{"learn":[15996.57385],"iteration":504,"passed_time":1.726996353,"remaining_time":1.692798406},
{"learn":[15984.75441],"iteration":505,"passed_time":1.729673424,"remaining_time":1.688653501},
{"learn":[15927.28259],"iteration":506,"passed_time":1.732450023,"remaining_time":1.684611167},
{"learn":[15882.00545],"iteration":507,"passed_time":1.735176435,"remaining_time":1.680525209},
{"learn":[15859.4968],"iteration":508,"passed_time":1.73878674,"remaining_time":1.677297228},
{"learn":[15856.42757],"iteration":509,"passed_time":1.741759766,"remaining_time":1.673455462},
{"learn":[15805.29369],"iteration":510,"passed_time":1.745548334,"remaining_time":1.670397525},
{"learn":[15750.4855],"iteration":511,"passed_time":1.748580103,"remaining_time":1.66661541},
{"learn":[15715.89034],"iteration":512,"passed_time":1.751244247,"remaining_time":1.662487228},
{"learn":[15710.07234],"iteration":513,"passed_time":1.755461959,"remaining_time":1.659833681},
{"learn":[15678.97417],"iteration":514,"passed_time":1.757997255,"remaining_time":1.655589648},
{"learn":[15631.59163],"iteration":515,"passed_time":1.760597993,"remaining_time":1.651413621},
{"learn":[15627.41555],"iteration":516,"passed_time":1.763251082,"remaining_time":1.647292597},
{"learn":[15603.6236],"iteration":517,"passed_time":1.765781167,"remaining_time":1.643062785},
{"learn":[15598.66714],"iteration":518,"passed_time":1.769079293,"remaining_time":1.639551329},
{"learn":[15545.59795],"iteration":519,"passed_time":1.772716925,"remaining_time":1.636354085},
{"learn":[15542.14141],"iteration":520,"passed_time":1.775571254,"remaining_time":1.632434992},
{"learn":[15528.1015],"iteration":521,"passed_time":1.778168779,"remaining_time":1.628284821},
{"learn":[15516.57151],"iteration":522,"passed_time":1.780736855,"remaining_time":1.624113728},
{"learn":[15499.03566],"iteration":523,"passed_time":1.783314125,"remaining_time":1.619957106},
{"learn":[15495.20338],"iteration":524,"passed_time":1.786022117,"remaining_time":1.615924773},
{"learn":[15483.2978],"iteration":525,"passed_time":1.788592329,"remaining_time":1.611773315},
{"learn":[15462.61746],"iteration":526,"passed_time":1.791241993,"remaining_time":1.607699171},
{"learn":[15412.23927],"iteration":527,"passed_time":1.794517064,"remaining_time":1.604189496},
{"learn":[15408.54744],"iteration":528,"passed_time":1.797365179,"remaining_time":1.600300565},
{"learn":[15404.47649],"iteration":529,"passed_time":1.800599956,"remaining_time":1.596758451},
{"learn":[15380.4302],"iteration":530,"passed_time":1.803846988,"remaining_time":1.593228319},
{"learn":[15357.88307],"iteration":531,"passed_time":1.807164436,"remaining_time":1.589761195},
{"learn":[15318.32764],"iteration":532,"passed_time":1.810599736,"remaining_time":1.586397893},
{"learn":[15308.80752],"iteration":533,"passed_time":1.813245493,"remaining_time":1.582345318},
{"learn":[15291.24332],"iteration":534,"passed_time":1.816007708,"remaining_time":1.578399223},
{"learn":[15257.55786],"iteration":535,"passed_time":1.818484414,"remaining_time":1.574210388},
{"learn":[15253.24916],"iteration":536,"passed_time":1.821072557,"remaining_time":1.570124011},
{"learn":[15247.93102],"iteration":537,"passed_time":1.82371569,"remaining_time":1.566090425},
{"learn":[15231.90305],"iteration":538,"passed_time":1.826346086,"remaining_time":1.562051105},
{"learn":[15190.17231],"iteration":539,"passed_time":1.828926735,"remaining_time":1.557974626},
{"learn":[15165.53918],"iteration":540,"passed_time":1.831544424,"remaining_time":1.553935103},
{"learn":[15138.80084],"iteration":541,"passed_time":1.834102529,"remaining_time":1.549850476},
{"learn":[15127.95924],"iteration":542,"passed_time":1.836565877,"remaining_time":1.545691723},
{"learn":[15113.42743],"iteration":543,"passed_time":1.838999584,"remaining_time":1.541514357},
{"learn":[15078.05353],"iteration":544,"passed_time":1.841694454,"remaining_time":1.537561425},
{"learn":[15067.74301],"iteration":545,"passed_time":1.844190448,"remaining_time":1.533447735},
{"learn":[15060.40125],"iteration":546,"passed_time":1.846661639,"remaining_time":1.529319419},
{"learn":[15043.38416],"iteration":547,"passed_time":1.849264385,"remaining_time":1.52530566},
{"learn":[15010.83428],"iteration":548,"passed_time":1.851937088,"remaining_time":1.521354511},
{"learn":[15003.05218],"iteration":549,"passed_time":1.854631535,"remaining_time":1.517425801},
{"learn":[14999.96516],"iteration":550,"passed_time":1.85719218,"remaining_time":1.513392538},
{"learn":[14996.72723],"iteration":551,"passed_time":1.85989537,"remaining_time":1.5094803},
{"learn":[14993.45535],"iteration":552,"passed_time":1.862491341,"remaining_time":1.505485768},
{"learn":[14959.06783],"iteration":553,"passed_time":1.865032869,"remaining_time":1.501452454},
{"learn":[14952.41037],"iteration":554,"passed_time":1.86775354,"remaining_time":1.497568154},
{"learn":[14899.53411],"iteration":555,"passed_time":1.870575466,"remaining_time":1.493768897},
{"learn":[14868.31329],"iteration":556,"passed_time":1.873290467,"remaining_time":1.489888109},
{"learn":[14861.3222],"iteration":557,"passed_time":1.87566087,"remaining_time":1.485738539},
{"learn":[14846.67238],"iteration":558,"passed_time":1.878381148,"remaining_time":1.481871353},
{"learn":[14836.86698],"iteration":559,"passed_time":1.881123016,"remaining_time":1.478025227},
{"learn":[14832.61823],"iteration":560,"passed_time":1.884156793,"remaining_time":1.474411466},
{"learn":[14784.71997],"iteration":561,"passed_time":1.886841786,"remaining_time":1.47052794},
{"learn":[14762.76776],"iteration":562,"passed_time":1.889366108,"remaining_time":1.46652396},
{"learn":[14754.03901],"iteration":563,"passed_time":1.892136814,"remaining_time":1.462715693},
{"learn":[14750.29242],"iteration":564,"passed_time":1.894997755,"remaining_time":1.458980573},
{"learn":[14731.73314],"iteration":565,"passed_time":1.897656105,"remaining_time":1.455093197},
{"learn":[14707.86705],"iteration":566,"passed_time":1.900834743,"remaining_time":1.451607485},
{"learn":[14678.1334],"iteration":567,"passed_time":1.904512055,"remaining_time":1.448502126},
{"learn":[14669.90959],"iteration":568,"passed_time":1.908364595,"remaining_time":1.445527488},
{"learn":[14665.16769],"iteration":569,"passed_time":1.912080663,"remaining_time":1.442446816},
{"learn":[14620.37368],"iteration":570,"passed_time":1.914940306,"remaining_time":1.438720475},
{"learn":[14598.1305],"iteration":571,"passed_time":1.917721396,"remaining_time":1.434938387},
{"learn":[14583.25985],"iteration":572,"passed_time":1.920583148,"remaining_time":1.431219903},
{"learn":[14576.17523],"iteration":573,"passed_time":1.923162471,"remaining_time":1.427294796},
{"learn":[14568.79289],"iteration":574,"passed_time":1.925811015,"remaining_time":1.423425533},
{"learn":[14551.21943],"iteration":575,"passed_time":1.928397349,"remaining_time":1.419514715},
{"learn":[14515.1452],"iteration":576,"passed_time":1.930871884,"remaining_time":1.415526529},
{"learn":[14492.70342],"iteration":577,"passed_time":1.933992297,"remaining_time":1.412015137},
{"learn":[14483.24686],"iteration":578,"passed_time":1.936983413,"remaining_time":1.408411082},
{"learn":[14480.42592],"iteration":579,"passed_time":1.939866836,"remaining_time":1.404731157},
{"learn":[14474.256],"iteration":580,"passed_time":1.94264758,"remaining_time":1.400979924},
{"learn":[14465.43068],"iteration":581,"passed_time":1.945195049,"remaining_time":1.397064485},
{"learn":[14418.07551],"iteration":582,"passed_time":1.947897937,"remaining_time":1.393264905},
{"learn":[14379.27417],"iteration":583,"passed_time":1.950614014,"remaining_time":1.389478476},
{"learn":[14373.05592],"iteration":584,"passed_time":1.953468779,"remaining_time":1.385794091},
{"learn":[14370.39108],"iteration":585,"passed_time":1.956256221,"remaining_time":1.382064975},
{"learn":[14353.35416],"iteration":586,"passed_time":1.958936365,"remaining_time":1.378263576},
{"learn":[14345.13384],"iteration":587,"passed_time":1.961870927,"remaining_time":1.374644255},
{"learn":[14329.53591],"iteration":588,"passed_time":1.964892246,"remaining_time":1.371087798},
{"learn":[14273.60317],"iteration":589,"passed_time":1.96751759,"remaining_time":1.367257986},
{"learn":[14244.56296],"iteration":590,"passed_time":1.970725259,"remaining_time":1.363835247},
{"learn":[14238.96541],"iteration":591,"passed_time":1.974174674,"remaining_time":1.360579843},
{"learn":[14219.79993],"iteration":592,"passed_time":1.977433696,"remaining_time":1.35719311},
{"learn":[14208.44176],"iteration":593,"passed_time":1.979956547,"remaining_time":1.353303633},
{"learn":[14204.83167],"iteration":594,"passed_time":1.982661788,"remaining_time":1.349542898},
{"learn":[14202.17411],"iteration":595,"passed_time":1.985370334,"remaining_time":1.345787944},
{"learn":[14198.55087],"iteration":596,"passed_time":1.988003173,"remaining_time":1.341985392},
{"learn":[14192.58202],"iteration":597,"passed_time":1.990444827,"remaining_time":1.338058228},
{"learn":[14183.60135],"iteration":598,"passed_time":1.993176251,"remaining_time":1.334330011},
{"learn":[14168.31476],"iteration":599,"passed_time":1.995707802,"remaining_time":1.330471868},
{"learn":[14164.96235],"iteration":600,"passed_time":1.998681988,"remaining_time":1.326912002},
{"learn":[14129.03785],"iteration":601,"passed_time":2.001573795,"remaining_time":1.323299619},
{"learn":[14078.77063],"iteration":602,"passed_time":2.004447016,"remaining_time":1.319677389},
{"learn":[14038.33147],"iteration":603,"passed_time":2.007180271,"remaining_time":1.315965873},
{"learn":[14007.1641],"iteration":604,"passed_time":2.009702402,"remaining_time":1.31211975},
{"learn":[13943.54954],"iteration":605,"passed_time":2.012154953,"remaining_time":1.308232758},
{"learn":[13941.03618],"iteration":606,"passed_time":2.014761189,"remaining_time":1.304449996},
{"learn":[13919.46558],"iteration":607,"passed_time":2.017491403,"remaining_time":1.300751036},
{"learn":[13860.36429],"iteration":608,"passed_time":2.02040106,"remaining_time":1.297170467},
{"learn":[13802.88111],"iteration":609,"passed_time":2.023242012,"remaining_time":1.293548172},
{"learn":[13798.94356],"iteration":610,"passed_time":2.026293448,"remaining_time":1.29006244},
{"learn":[13741.92065],"iteration":611,"passed_time":2.028920943,"remaining_time":1.286309356},
{"learn":[13724.91589],"iteration":612,"passed_time":2.031521591,"remaining_time":1.282542994},
{"learn":[13687.13146],"iteration":613,"passed_time":2.034120835,"remaining_time":1.278779547},
{"learn":[13683.91523],"iteration":614,"passed_time":2.036585247,"remaining_time":1.27493548},
{"learn":[13681.26017],"iteration":615,"passed_time":2.039263622,"remaining_time":1.271229271},
{"learn":[13677.85251],"iteration":616,"passed_time":2.041789886,"remaining_time":1.267431971},
{"learn":[13672.12196],"iteration":617,"passed_time":2.04438973,"remaining_time":1.263684267},
{"learn":[13650.68787],"iteration":618,"passed_time":2.047538854,"remaining_time":1.260278358},
{"learn":[13642.05498],"iteration":619,"passed_time":2.050284758,"remaining_time":1.256626142},
{"learn":[13634.32804],"iteration":620,"passed_time":2.052881663,"remaining_time":1.25288591},
{"learn":[13630.94092],"iteration":621,"passed_time":2.05592296,"remaining_time":1.249419419},
{"learn":[13627.47134],"iteration":622,"passed_time":2.058821059,"remaining_time":1.245867639},
{"learn":[13621.64606],"iteration":623,"passed_time":2.061433715,"remaining_time":1.242145956},
{"learn":[13618.06519],"iteration":624,"passed_time":2.06419327,"remaining_time":1.238515962},
{"learn":[13601.62535],"iteration":625,"passed_time":2.066739798,"remaining_time":1.234761477},
{"learn":[13598.52346],"iteration":626,"passed_time":2.069527626,"remaining_time":1.231154393},
{"learn":[13583.7085],"iteration":627,"passed_time":2.074270722,"remaining_time":1.228708135},
{"learn":[13579.85462],"iteration":628,"passed_time":2.077827351,"remaining_time":1.225554765},
{"learn":[13576.25575],"iteration":629,"passed_time":2.080426099,"remaining_time":1.22183755},
{"learn":[13562.30409],"iteration":630,"passed_time":2.08500336,"remaining_time":1.219280887},
{"learn":[13541.89129],"iteration":631,"passed_time":2.119946699,"remaining_time":1.234399343},
{"learn":[13539.29183],"iteration":632,"passed_time":2.128739834,"remaining_time":1.234198292},
{"learn":[13525.85853],"iteration":633,"passed_time":2.133264721,"remaining_time":1.231506132},
{"learn":[13503.96822],"iteration":634,"passed_time":2.137606589,"remaining_time":1.228703},
{"learn":[13498.15468],"iteration":635,"passed_time":2.141002226,"remaining_time":1.225353475},
{"learn":[13492.81606],"iteration":636,"passed_time":2.144203623,"remaining_time":1.221893117},
{"learn":[13489.4204],"iteration":637,"passed_time":2.147411441,"remaining_time":1.218437212},
{"learn":[13482.54799],"iteration":638,"passed_time":2.150787656,"remaining_time":1.21507722},
{"learn":[13477.065],"iteration":639,"passed_time":2.154242761,"remaining_time":1.211761553},
{"learn":[13461.58038],"iteration":640,"passed_time":2.159367245,"remaining_time":1.209380407},
{"learn":[13458.81205],"iteration":641,"passed_time":2.163357736,"remaining_time":1.206358364},
{"learn":[13453.6889],"iteration":642,"passed_time":2.166619396,"remaining_time":1.202928654},
{"learn":[13448.42012],"iteration":643,"passed_time":2.171028794,"remaining_time":1.200133929},
{"learn":[13446.35014],"iteration":644,"passed_time":2.174612775,"remaining_time":1.196879899},
{"learn":[13437.03692],"iteration":645,"passed_time":2.178099718,"remaining_time":1.193571672},
{"learn":[13424.16367],"iteration":646,"passed_time":2.181390178,"remaining_time":1.190155692},
{"learn":[13410.71575],"iteration":647,"passed_time":2.184855916,"remaining_time":1.186835312},
{"learn":[13404.71277],"iteration":648,"passed_time":2.188016513,"remaining_time":1.183349455},
{"learn":[13399.69703],"iteration":649,"passed_time":2.191799195,"remaining_time":1.180199567},
{"learn":[13392.38425],"iteration":650,"passed_time":2.195055035,"remaining_time":1.176765295},
{"learn":[13388.31403],"iteration":651,"passed_time":2.197957073,"remaining_time":1.173142732},
{"learn":[13362.81582],"iteration":652,"passed_time":2.202107378,"remaining_time":1.170185697},
{"learn":[13333.82637],"iteration":653,"passed_time":2.206066944,"remaining_time":1.167124102},
{"learn":[13268.95772],"iteration":654,"passed_time":2.208962069,"remaining_time":1.163499105},
{"learn":[13225.88997],"iteration":655,"passed_time":2.212353424,"remaining_time":1.160136551},
{"learn":[13221.06656],"iteration":656,"passed_time":2.214859415,"remaining_time":1.156311689},
{"learn":[13199.29817],"iteration":657,"passed_time":2.218595371,"remaining_time":1.153130117},
{"learn":[13153.76373],"iteration":658,"passed_time":2.221461055,"remaining_time":1.14949654},
{"learn":[13148.55621],"iteration":659,"passed_time":2.225096475,"remaining_time":1.14626182},
{"learn":[13123.39486],"iteration":660,"passed_time":2.227912676,"remaining_time":1.142605745},
{"learn":[13086.07528],"iteration":661,"passed_time":2.230831434,"remaining_time":1.139004569},
{"learn":[13051.01089],"iteration":662,"passed_time":2.233564068,"remaining_time":1.135310846},
{"learn":[13044.04148],"iteration":663,"passed_time":2.236113613,"remaining_time":1.131527371},
{"learn":[13002.34636],"iteration":664,"passed_time":2.238575916,"remaining_time":1.127703657},
{"learn":[12947.78233],"iteration":665,"passed_time":2.241232166,"remaining_time":1.123981296},
{"learn":[12943.20498],"iteration":666,"passed_time":2.243868058,"remaining_time":1.120251969},
{"learn":[12937.79022],"iteration":667,"passed_time":2.246385533,"remaining_time":1.116467061},
{"learn":[12898.49511],"iteration":668,"passed_time":2.249035559,"remaining_time":1.112751524},
{"learn":[12871.65095],"iteration":669,"passed_time":2.251727693,"remaining_time":1.109059909},
{"learn":[12844.63011],"iteration":670,"passed_time":2.254187983,"remaining_time":1.105257595},
{"learn":[12799.94602],"iteration":671,"passed_time":2.25669424,"remaining_time":1.101481712},
{"learn":[12774.95044],"iteration":672,"passed_time":2.259222212,"remaining_time":1.097720154},
{"learn":[12721.5119],"iteration":673,"passed_time":2.261652401,"remaining_time":1.09391496},
{"learn":[12679.67236],"iteration":674,"passed_time":2.264134044,"remaining_time":1.090138614},
{"learn":[12647.10381],"iteration":675,"passed_time":2.26653889,"remaining_time":1.086329291},
{"learn":[12633.91692],"iteration":676,"passed_time":2.269052979,"remaining_time":1.082576237},
{"learn":[12608.97747],"iteration":677,"passed_time":2.271675324,"remaining_time":1.078878251},
{"learn":[12594.66214],"iteration":678,"passed_time":2.274176313,"remaining_time":1.075126063},
{"learn":[12568.81393],"iteration":679,"passed_time":2.276649739,"remaining_time":1.071364583},
{"learn":[12534.78474],"iteration":680,"passed_time":2.27915156,"remaining_time":1.067620188},
{"learn":[12508.14938],"iteration":681,"passed_time":2.281795258,"remaining_time":1.063945589},
{"learn":[12473.60816],"iteration":682,"passed_time":2.284419478,"remaining_time":1.06026497},
{"learn":[12470.52179],"iteration":683,"passed_time":2.287166334,"remaining_time":1.056644096},
{"learn":[12467.85647],"iteration":684,"passed_time":2.289767084,"remaining_time":1.052958586},
{"learn":[12428.42426],"iteration":685,"passed_time":2.292457946,"remaining_time":1.049317486},
{"learn":[12411.10995],"iteration":686,"passed_time":2.294922558,"remaining_time":1.045576071},
{"learn":[12407.91174],"iteration":687,"passed_time":2.297443608,"remaining_time":1.041863962},
{"learn":[12399.23026],"iteration":688,"passed_time":2.300053865,"remaining_time":1.038195576},
{"learn":[12397.24423],"iteration":689,"passed_time":2.303038529,"remaining_time":1.034698469},
{"learn":[12394.83706],"iteration":690,"passed_time":2.305973631,"remaining_time":1.031180683},
{"learn":[12370.79263],"iteration":691,"passed_time":2.308784964,"remaining_time":1.027609493},
{"learn":[12365.50082],"iteration":692,"passed_time":2.311324367,"remaining_time":1.02392003},
{"learn":[12352.75661],"iteration":693,"passed_time":2.313911069,"remaining_time":1.020254736},
{"learn":[12344.12126],"iteration":694,"passed_time":2.316460331,"remaining_time":1.016576116},
{"learn":[12312.91545],"iteration":695,"passed_time":2.31901904,"remaining_time":1.012904868},
{"learn":[12291.10846],"iteration":696,"passed_time":2.321457834,"remaining_time":1.009184683},
{"learn":[12255.50369],"iteration":697,"passed_time":2.324026634,"remaining_time":1.005524418},
{"learn":[12233.27193],"iteration":698,"passed_time":2.326554117,"remaining_time":1.001849484},
{"learn":[12218.58472],"iteration":699,"passed_time":2.329017324,"remaining_time":0.9981502816},
{"learn":[12215.56997],"iteration":700,"passed_time":2.331647597,"remaining_time":0.994525865},
{"learn":[12209.97366],"iteration":701,"passed_time":2.334482203,"remaining_time":0.9909910208},
{"learn":[12190.92518],"iteration":702,"passed_time":2.338144133,"remaining_time":0.9878076918},
{"learn":[12172.68045],"iteration":703,"passed_time":2.341811451,"remaining_time":0.9846252691},
{"learn":[12155.19418],"iteration":704,"passed_time":2.344787806,"remaining_time":0.9811523442},
{"learn":[12145.61172],"iteration":705,"passed_time":2.348166979,"remaining_time":0.977848572},
{"learn":[12128.8157],"iteration":706,"passed_time":2.350871669,"remaining_time":0.9742650622},
{"learn":[12115.7063],"iteration":707,"passed_time":2.353772712,"remaining_time":0.970765017},
{"learn":[12105.43121],"iteration":708,"passed_time":2.357055681,"remaining_time":0.9674234178},
{"learn":[12092.29138],"iteration":709,"passed_time":2.360431262,"remaining_time":0.9641198111},
{"learn":[12081.2674],"iteration":710,"passed_time":2.363250078,"remaining_time":0.9605896943},
{"learn":[12062.21509],"iteration":711,"passed_time":2.366491895,"remaining_time":0.9572326767},
{"learn":[12048.004],"iteration":712,"passed_time":2.369338957,"remaining_time":0.9537170835},
{"learn":[12031.84211],"iteration":713,"passed_time":2.372005898,"remaining_time":0.9501312141},
{"learn":[12016.3255],"iteration":714,"passed_time":2.374434245,"remaining_time":0.9464528107},
{"learn":[12001.42067],"iteration":715,"passed_time":2.376927814,"remaining_time":0.9428037697},
{"learn":[11981.1547],"iteration":716,"passed_time":2.379472768,"remaining_time":0.9391782332},
{"learn":[11964.91803],"iteration":717,"passed_time":2.382063486,"remaining_time":0.9355736813},
{"learn":[11938.91068],"iteration":718,"passed_time":2.384975083,"remaining_time":0.9320973551},
{"learn":[11910.69385],"iteration":719,"passed_time":2.387395606,"remaining_time":0.9284316247},
{"learn":[11899.92638],"iteration":720,"passed_time":2.390078052,"remaining_time":0.9248707025},
{"learn":[11896.87083],"iteration":721,"passed_time":2.392550802,"remaining_time":0.9212314721},
{"learn":[11895.10764],"iteration":722,"passed_time":2.395226744,"remaining_time":0.9176733169},
{"learn":[11882.94595],"iteration":723,"passed_time":2.398025257,"remaining_time":0.9141643246},
{"learn":[11871.08834],"iteration":724,"passed_time":2.400570107,"remaining_time":0.9105610749},
{"learn":[11867.10976],"iteration":725,"passed_time":2.403161449,"remaining_time":0.906978288},
{"learn":[11853.30297],"iteration":726,"passed_time":2.405674847,"remaining_time":0.9033689592},
{"learn":[11847.06644],"iteration":727,"passed_time":2.408188517,"remaining_time":0.8997627428},
{"learn":[11826.83251],"iteration":728,"passed_time":2.410823094,"remaining_time":0.8962044697},
{"learn":[11817.82599],"iteration":729,"passed_time":2.413352389,"remaining_time":0.8926097878},
{"learn":[11813.03605],"iteration":730,"passed_time":2.415959848,"remaining_time":0.8890467838},
{"learn":[11803.08478],"iteration":731,"passed_time":2.418592678,"remaining_time":0.8854956798},
{"learn":[11785.3988],"iteration":732,"passed_time":2.421104615,"remaining_time":0.8819030453},
{"learn":[11771.46511],"iteration":733,"passed_time":2.423505388,"remaining_time":0.8782730696},
{"learn":[11752.73872],"iteration":734,"passed_time":2.426103842,"remaining_time":0.8747177116},
{"learn":[11738.59916],"iteration":735,"passed_time":2.428687856,"remaining_time":0.8711597743},
{"learn":[11724.99053],"iteration":736,"passed_time":2.431291173,"remaining_time":0.8676113684},
{"learn":[11711.88323],"iteration":737,"passed_time":2.435187656,"remaining_time":0.8645246148},
{"learn":[11703.42424],"iteration":738,"passed_time":2.438808243,"remaining_time":0.8613382294},
{"learn":[11700.74294],"iteration":739,"passed_time":2.441897909,"remaining_time":0.8579641301},
{"learn":[11688.96601],"iteration":740,"passed_time":2.445044557,"remaining_time":0.8546107158},
{"learn":[11676.43155],"iteration":741,"passed_time":2.44767598,"remaining_time":0.8510787101},
{"learn":[11644.23911],"iteration":742,"passed_time":2.450487654,"remaining_time":0.8476114765},
{"learn":[11641.2408],"iteration":743,"passed_time":2.453260375,"remaining_time":0.844132602},
{"learn":[11623.27471],"iteration":744,"passed_time":2.456046884,"remaining_time":0.8406603429},
{"learn":[11621.69169],"iteration":745,"passed_time":2.45874367,"remaining_time":0.837159373},
{"learn":[11605.36353],"iteration":746,"passed_time":2.461534077,"remaining_time":0.8336922644},
{"learn":[11602.25131],"iteration":747,"passed_time":2.464339927,"remaining_time":0.830232168},
{"learn":[11597.93767],"iteration":748,"passed_time":2.467614313,"remaining_time":0.8269308312},
{"learn":[11591.14803],"iteration":749,"passed_time":2.470085543,"remaining_time":0.8233618477},
{"learn":[11588.41492],"iteration":750,"passed_time":2.472895577,"remaining_time":0.8199081208},
{"learn":[11581.71506],"iteration":751,"passed_time":2.475530926,"remaining_time":0.816398497},
{"learn":[11573.01803],"iteration":752,"passed_time":2.478196254,"remaining_time":0.812901029},
{"learn":[11557.02911],"iteration":753,"passed_time":2.481191313,"remaining_time":0.8095133461},
{"learn":[11524.73749],"iteration":754,"passed_time":2.484603348,"remaining_time":0.8062620137},
{"learn":[11518.24345],"iteration":755,"passed_time":2.487234762,"remaining_time":0.8027583096},
{"learn":[11491.48328],"iteration":756,"passed_time":2.489713002,"remaining_time":0.7992077405},
{"learn":[11481.5252],"iteration":757,"passed_time":2.492282035,"remaining_time":0.7956889873},
{"learn":[11477.80373],"iteration":758,"passed_time":2.495068342,"remaining_time":0.7922417266},
{"learn":[11461.27515],"iteration":759,"passed_time":2.497819404,"remaining_time":0.7887850749},
{"learn":[11444.99601],"iteration":760,"passed_time":2.500478053,"remaining_time":0.7853012546},
{"learn":[11440.60955],"iteration":761,"passed_time":2.503243347,"remaining_time":0.7818529089},
{"learn":[11421.56055],"iteration":762,"passed_time":2.5058493,"remaining_time":0.7783568598},
{"learn":[11391.5597],"iteration":763,"passed_time":2.508405694,"remaining_time":0.7748478323},
{"learn":[11384.20396],"iteration":764,"passed_time":2.511003768,"remaining_time":0.7713540986},
{"learn":[11380.61786],"iteration":765,"passed_time":2.513549372,"remaining_time":0.7678466751},
{"learn":[11349.06933],"iteration":766,"passed_time":2.516073393,"remaining_time":0.7643352027},
{"learn":[11346.45236],"iteration":767,"passed_time":2.518771425,"remaining_time":0.7608788678},
{"learn":[11342.82734],"iteration":768,"passed_time":2.521543472,"remaining_time":0.7574467388},
{"learn":[11332.18277],"iteration":769,"passed_time":2.524227621,"remaining_time":0.7539900686},
{"learn":[11312.9941],"iteration":770,"passed_time":2.526792948,"remaining_time":0.7505001103},
{"learn":[11300.09383],"iteration":771,"passed_time":2.5299068,"remaining_time":0.747174547},
{"learn":[11293.74991],"iteration":772,"passed_time":2.532837615,"remaining_time":0.7437957807},
{"learn":[11290.43153],"iteration":773,"passed_time":2.535634541,"remaining_time":0.7403790779},
{"learn":[11284.66178],"iteration":774,"passed_time":2.538555101,"remaining_time":0.7369998679},
{"learn":[11268.9653],"iteration":775,"passed_time":2.542808038,"remaining_time":0.7340064439},
{"learn":[11267.19815],"iteration":776,"passed_time":2.546655064,"remaining_time":0.730893281},
{"learn":[11255.85441],"iteration":777,"passed_time":2.551429259,"remaining_time":0.7280427964},
{"learn":[11241.10162],"iteration":778,"passed_time":2.555067521,"remaining_time":0.7248651119},
{"learn":[11238.52888],"iteration":779,"passed_time":2.557273327,"remaining_time":0.7212822203},
{"learn":[11215.21669],"iteration":780,"passed_time":2.559497369,"remaining_time":0.7177079691},
{"learn":[11201.96452],"iteration":781,"passed_time":2.561843026,"remaining_time":0.7141710738},
{"learn":[11179.573],"iteration":782,"passed_time":2.56424798,"remaining_time":0.7106536546},
{"learn":[11145.67361],"iteration":783,"passed_time":2.566461256,"remaining_time":0.7070862644},
{"learn":[11140.47236],"iteration":784,"passed_time":2.568903297,"remaining_time":0.7035849795},
{"learn":[11127.41954],"iteration":785,"passed_time":2.571192393,"remaining_time":0.7000447481},
{"learn":[11100.83751],"iteration":786,"passed_time":2.573361296,"remaining_time":0.6964751666},
{"learn":[11068.24597],"iteration":787,"passed_time":2.576182551,"remaining_time":0.6930846458},
{"learn":[11065.76896],"iteration":788,"passed_time":2.578757642,"remaining_time":0.6896297369},
{"learn":[11049.39477],"iteration":789,"passed_time":2.581095899,"remaining_time":0.6861140997},
{"learn":[11045.81932],"iteration":790,"passed_time":2.58337062,"remaining_time":0.6825846518},
{"learn":[11034.81137],"iteration":791,"passed_time":2.585543323,"remaining_time":0.6790315798},
{"learn":[11021.22833],"iteration":792,"passed_time":2.587901222,"remaining_time":0.6755303315},
{"learn":[11017.93341],"iteration":793,"passed_time":2.590309868,"remaining_time":0.6720451295},
{"learn":[11016.27904],"iteration":794,"passed_time":2.592722132,"remaining_time":0.6685635687},
{"learn":[11013.72341],"iteration":795,"passed_time":2.594996848,"remaining_time":0.6650494434},
{"learn":[10990.46992],"iteration":796,"passed_time":2.597319743,"remaining_time":0.6615507},
{"learn":[10986.47212],"iteration":797,"passed_time":2.599780126,"remaining_time":0.6580897062},
{"learn":[10975.35821],"iteration":798,"passed_time":2.60223308,"remaining_time":0.654629348},
{"learn":[10971.68566],"iteration":799,"passed_time":2.604545307,"remaining_time":0.6511363268},
{"learn":[10958.06793],"iteration":800,"passed_time":2.607191698,"remaining_time":0.6477292734},
{"learn":[10950.88817],"iteration":801,"passed_time":2.60935229,"remaining_time":0.6442041813},
{"learn":[10939.99002],"iteration":802,"passed_time":2.611600169,"remaining_time":0.6407039019},
{"learn":[10936.94229],"iteration":803,"passed_time":2.613949117,"remaining_time":0.6372313767},
{"learn":[10933.34351],"iteration":804,"passed_time":2.616194465,"remaining_time":0.6337365473},
{"learn":[10930.57341],"iteration":805,"passed_time":2.618408946,"remaining_time":0.6302373891},
{"learn":[10928.21189],"iteration":806,"passed_time":2.620729646,"remaining_time":0.6267668175},
{"learn":[10919.87893],"iteration":807,"passed_time":2.623050257,"remaining_time":0.6232990709},
{"learn":[10900.4232],"iteration":808,"passed_time":2.625339009,"remaining_time":0.6198266387},
{"learn":[10887.23132],"iteration":809,"passed_time":2.627871809,"remaining_time":0.616414375},
{"learn":[10875.27711],"iteration":810,"passed_time":2.630211299,"remaining_time":0.6129592299},
{"learn":[10863.02438],"iteration":811,"passed_time":2.632727642,"remaining_time":0.6095477792},
{"learn":[10837.70234],"iteration":812,"passed_time":2.63508198,"remaining_time":0.6061012672},
{"learn":[10814.8911],"iteration":813,"passed_time":2.637318667,"remaining_time":0.6026305554},
{"learn":[10808.07351],"iteration":814,"passed_time":2.639570518,"remaining_time":0.5991663138},
{"learn":[10803.29229],"iteration":815,"passed_time":2.641814386,"remaining_time":0.5957032439},
{"learn":[10786.91502],"iteration":816,"passed_time":2.644286662,"remaining_time":0.5922943196},
{"learn":[10784.01976],"iteration":817,"passed_time":2.646639824,"remaining_time":0.5888611834},
{"learn":[10782.08756],"iteration":818,"passed_time":2.649196792,"remaining_time":0.5854757257},
{"learn":[10755.58573],"iteration":819,"passed_time":2.651828662,"remaining_time":0.5821087307},
{"learn":[10751.56797],"iteration":820,"passed_time":2.653724617,"remaining_time":0.5785830772},
{"learn":[10717.87314],"iteration":821,"passed_time":2.65580329,"remaining_time":0.5751009558},
{"learn":[10706.34181],"iteration":822,"passed_time":2.657760622,"remaining_time":0.5715961484},
{"learn":[10695.2506],"iteration":823,"passed_time":2.65968339,"remaining_time":0.5680877144},
{"learn":[10684.57827],"iteration":824,"passed_time":2.661601127,"remaining_time":0.5645820572},
{"learn":[10674.305],"iteration":825,"passed_time":2.663834307,"remaining_time":0.5611466942},
{"learn":[10664.41224],"iteration":826,"passed_time":2.665745992,"remaining_time":0.5576469851},
{"learn":[10654.51077],"iteration":827,"passed_time":2.667647,"remaining_time":0.5541488937},
{"learn":[10644.95584],"iteration":828,"passed_time":2.669588594,"remaining_time":0.5506630272},
{"learn":[10635.5928],"iteration":829,"passed_time":2.671768074,"remaining_time":0.5472296056},
{"learn":[10610.09288],"iteration":830,"passed_time":2.674078098,"remaining_time":0.5438257503},
{"learn":[10605.53029],"iteration":831,"passed_time":2.676232571,"remaining_time":0.5403931154},
{"learn":[10581.78302],"iteration":832,"passed_time":2.678516121,"remaining_time":0.5369894263},
{"learn":[10575.08218],"iteration":833,"passed_time":2.680409088,"remaining_time":0.5335106819},
{"learn":[10552.56024],"iteration":834,"passed_time":2.682367413,"remaining_time":0.5300486505},
{"learn":[10549.01257],"iteration":835,"passed_time":2.684217968,"remaining_time":0.5265690751},
{"learn":[10534.73559],"iteration":836,"passed_time":2.686201838,"remaining_time":0.5231193543},
{"learn":[10518.06407],"iteration":837,"passed_time":2.688211283,"remaining_time":0.5196780762},
{"learn":[10503.54083],"iteration":838,"passed_time":2.690231235,"remaining_time":0.5162422275},
{"learn":[10502.17225],"iteration":839,"passed_time":2.692246267,"remaining_time":0.5128088127},
{"learn":[10496.96217],"iteration":840,"passed_time":2.694142773,"remaining_time":0.5093563626},
{"learn":[10478.35799],"iteration":841,"passed_time":2.6962114,"remaining_time":0.5059399065},
{"learn":[10473.19827],"iteration":842,"passed_time":2.6982528,"remaining_time":0.5025215771},
{"learn":[10470.95904],"iteration":843,"passed_time":2.700122207,"remaining_time":0.4990747207},
{"learn":[10457.53164],"iteration":844,"passed_time":2.701986038,"remaining_time":0.495630575},
{"learn":[10436.72181],"iteration":845,"passed_time":2.703999258,"remaining_time":0.4922173591},
{"learn":[10434.23809],"iteration":846,"passed_time":2.706022585,"remaining_time":0.4888092744},
{"learn":[10421.98445],"iteration":847,"passed_time":2.707912068,"remaining_time":0.485380465},
{"learn":[10419.88852],"iteration":848,"passed_time":2.709803891,"remaining_time":0.481955698},
{"learn":[10401.75605],"iteration":849,"passed_time":2.711844263,"remaining_time":0.4785607522},
{"learn":[10399.05983],"iteration":850,"passed_time":2.713978156,"remaining_time":0.4751853646},
{"learn":[10395.96505],"iteration":851,"passed_time":2.716013961,"remaining_time":0.4717958524},
{"learn":[10383.07367],"iteration":852,"passed_time":2.717965119,"remaining_time":0.4683949267},
{"learn":[10372.26902],"iteration":853,"passed_time":2.719870893,"remaining_time":0.4649896375},
{"learn":[10369.49103],"iteration":854,"passed_time":2.72413213,"remaining_time":0.4619873203},
{"learn":[10349.42397],"iteration":855,"passed_time":2.726779367,"remaining_time":0.4587105477},
{"learn":[10346.99207],"iteration":856,"passed_time":2.728745654,"remaining_time":0.4553216202},
{"learn":[10344.87003],"iteration":857,"passed_time":2.730734414,"remaining_time":0.4519397282},
{"learn":[10335.8728],"iteration":858,"passed_time":2.732669546,"remaining_time":0.448552277},
{"learn":[10318.7206],"iteration":859,"passed_time":2.734656575,"remaining_time":0.4451766517},
{"learn":[10316.5737],"iteration":860,"passed_time":2.736647503,"remaining_time":0.4418048815},
{"learn":[10309.33757],"iteration":861,"passed_time":2.739088935,"remaining_time":0.4385084375},
{"learn":[10300.59077],"iteration":862,"passed_time":2.741350118,"remaining_time":0.4351853605},
{"learn":[10280.95578],"iteration":863,"passed_time":2.743613463,"remaining_time":0.4318650821},
{"learn":[10257.18609],"iteration":864,"passed_time":2.74560694,"remaining_time":0.4285051294},
{"learn":[10248.95704],"iteration":865,"passed_time":2.747495276,"remaining_time":0.4251320636},
{"learn":[10245.09337],"iteration":866,"passed_time":2.749648539,"remaining_time":0.4218030631},
{"learn":[10230.99368],"iteration":867,"passed_time":2.751737532,"remaining_time":0.418466998},
{"learn":[10209.19171],"iteration":868,"passed_time":2.753918209,"remaining_time":0.4151476242},
{"learn":[10206.82351],"iteration":869,"passed_time":2.756180949,"remaining_time":0.4118431303},
{"learn":[10200.89663],"iteration":870,"passed_time":2.758331511,"remaining_time":0.4085244144},
{"learn":[10189.45703],"iteration":871,"passed_time":2.760376876,"remaining_time":0.4051929359},
{"learn":[10147.04571],"iteration":872,"passed_time":2.762314271,"remaining_time":0.4018486969},
{"learn":[10143.61393],"iteration":873,"passed_time":2.764196769,"remaining_time":0.398499763},
{"learn":[10141.2454],"iteration":874,"passed_time":2.766144719,"remaining_time":0.3951635313},
{"learn":[10136.89579],"iteration":875,"passed_time":2.767999751,"remaining_time":0.3918173164},
{"learn":[10134.18252],"iteration":876,"passed_time":2.770094081,"remaining_time":0.3885080639},
{"learn":[10127.35719],"iteration":877,"passed_time":2.771964558,"remaining_time":0.3851704739},
{"learn":[10124.72949],"iteration":878,"passed_time":2.773965771,"remaining_time":0.3818542187},
{"learn":[10106.8586],"iteration":879,"passed_time":2.775834362,"remaining_time":0.3785228676},
{"learn":[10092.19747],"iteration":880,"passed_time":2.777750631,"remaining_time":0.375201277},
{"learn":[10063.26445],"iteration":881,"passed_time":2.779643059,"remaining_time":0.3718796837},
{"learn":[10054.11576],"iteration":882,"passed_time":2.781860637,"remaining_time":0.3686044106},
{"learn":[10051.00539],"iteration":883,"passed_time":2.784210759,"remaining_time":0.3653489232},
{"learn":[10042.32113],"iteration":884,"passed_time":2.786380728,"remaining_time":0.362072072},
{"learn":[10028.68703],"iteration":885,"passed_time":2.788366043,"remaining_time":0.3587739604},
{"learn":[10018.69122],"iteration":886,"passed_time":2.790277338,"remaining_time":0.355469379},
{"learn":[9991.793838],"iteration":887,"passed_time":2.792196548,"remaining_time":0.352168934},
{"learn":[9972.854908],"iteration":888,"passed_time":2.79478989,"remaining_time":0.348955768},
{"learn":[9967.913594],"iteration":889,"passed_time":2.796825312,"remaining_time":0.3456750385},
{"learn":[9950.145486],"iteration":890,"passed_time":2.798838037,"remaining_time":0.3423943278},
{"learn":[9933.67401],"iteration":891,"passed_time":2.800700471,"remaining_time":0.3390982633},
{"learn":[9913.945169],"iteration":892,"passed_time":2.802970189,"remaining_time":0.3358542108},
{"learn":[9895.929369],"iteration":893,"passed_time":2.804993123,"remaining_time":0.3325830773},
{"learn":[9886.468725],"iteration":894,"passed_time":2.807465674,"remaining_time":0.3293674813},
{"learn":[9875.715262],"iteration":895,"passed_time":2.809349611,"remaining_time":0.3260852227},
{"learn":[9870.919961],"iteration":896,"passed_time":2.81125571,"remaining_time":0.3228086267},
{"learn":[9862.712116],"iteration":897,"passed_time":2.813039514,"remaining_time":0.319521192},
{"learn":[9846.123811],"iteration":898,"passed_time":2.815049178,"remaining_time":0.3162624772},
{"learn":[9843.426996],"iteration":899,"passed_time":2.817434445,"remaining_time":0.3130482717},
{"learn":[9835.147781],"iteration":900,"passed_time":2.819476677,"remaining_time":0.3097982142},
{"learn":[9825.625341],"iteration":901,"passed_time":2.821388173,"remaining_time":0.3065366308},
{"learn":[9820.106275],"iteration":902,"passed_time":2.823258131,"remaining_time":0.3032735756},
{"learn":[9814.411394],"iteration":903,"passed_time":2.825153514,"remaining_time":0.3000163024},
{"learn":[9812.958334],"iteration":904,"passed_time":2.827108095,"remaining_time":0.2967682531},
{"learn":[9798.794139],"iteration":905,"passed_time":2.829273084,"remaining_time":0.2935448896},
{"learn":[9765.311355],"iteration":906,"passed_time":2.831244368,"remaining_time":0.290303998},
{"learn":[9752.211531],"iteration":907,"passed_time":2.83346264,"remaining_time":0.2870909283},
{"learn":[9748.020023],"iteration":908,"passed_time":2.835631667,"remaining_time":0.2838751174},
{"learn":[9746.883335],"iteration":909,"passed_time":2.837684367,"remaining_time":0.2806501023},
{"learn":[9724.190852],"iteration":910,"passed_time":2.839817545,"remaining_time":0.2774355231},
{"learn":[9722.121373],"iteration":911,"passed_time":2.841880136,"remaining_time":0.2742165044},
{"learn":[9701.414635],"iteration":912,"passed_time":2.844072132,"remaining_time":0.2710123499},
{"learn":[9698.255254],"iteration":913,"passed_time":2.846315649,"remaining_time":0.267815258},
{"learn":[9693.555683],"iteration":914,"passed_time":2.849075913,"remaining_time":0.2646682543},
{"learn":[9677.728153],"iteration":915,"passed_time":2.851598358,"remaining_time":0.2615002861},
{"learn":[9673.500197],"iteration":916,"passed_time":2.855043322,"remaining_time":0.2584172254},
{"learn":[9660.057766],"iteration":917,"passed_time":2.85803558,"remaining_time":0.2552929385},
{"learn":[9654.815708],"iteration":918,"passed_time":2.860695699,"remaining_time":0.2521396645},
{"learn":[9652.40785],"iteration":919,"passed_time":2.863563292,"remaining_time":0.2490055037},
{"learn":[9634.393941],"iteration":920,"passed_time":2.867053949,"remaining_time":0.2459253658},
{"learn":[9631.646778],"iteration":921,"passed_time":2.869606252,"remaining_time":0.242764954},
{"learn":[9612.569393],"iteration":922,"passed_time":2.872490134,"remaining_time":0.2396335215},
{"learn":[9597.176797],"iteration":923,"passed_time":2.875622608,"remaining_time":0.2365230716},
{"learn":[9590.428239],"iteration":924,"passed_time":2.878419994,"remaining_time":0.2333854049},
{"learn":[9589.275923],"iteration":925,"passed_time":2.881385796,"remaining_time":0.2302619318},
{"learn":[9585.686351],"iteration":926,"passed_time":2.884355997,"remaining_time":0.2271391454},
{"learn":[9580.247378],"iteration":927,"passed_time":2.887565242,"remaining_time":0.2240352343},
{"learn":[9577.78691],"iteration":928,"passed_time":2.89076875,"remaining_time":0.2209306579},
{"learn":[9574.899811],"iteration":929,"passed_time":2.897257651,"remaining_time":0.2180731565},
{"learn":[9566.587361],"iteration":930,"passed_time":2.900849086,"remaining_time":0.2149931116},
{"learn":[9547.952819],"iteration":931,"passed_time":2.904526757,"remaining_time":0.2119182613},
{"learn":[9545.188223],"iteration":932,"passed_time":2.90830978,"remaining_time":0.2088496841},
{"learn":[9542.430546],"iteration":933,"passed_time":2.912686679,"remaining_time":0.2058215426},
{"learn":[9539.775821],"iteration":934,"passed_time":2.916806851,"remaining_time":0.2027726688},
{"learn":[9524.086057],"iteration":935,"passed_time":2.921181094,"remaining_time":0.1997388782},
{"learn":[9509.330903],"iteration":936,"passed_time":2.925257319,"remaining_time":0.196682189},
{"learn":[9507.926833],"iteration":937,"passed_time":2.929250749,"remaining_time":0.1936178533},
{"learn":[9494.670967],"iteration":938,"passed_time":2.933080844,"remaining_time":0.1905409281},
{"learn":[9486.453203],"iteration":939,"passed_time":2.937259531,"remaining_time":0.1874846509},
{"learn":[9478.959037],"iteration":940,"passed_time":2.941288047,"remaining_time":0.1844165726},
{"learn":[9471.633103],"iteration":941,"passed_time":2.944930923,"remaining_time":0.1813227108},
{"learn":[9465.247208],"iteration":942,"passed_time":2.948415097,"remaining_time":0.1782180917},
{"learn":[9448.25061],"iteration":943,"passed_time":2.95237331,"remaining_time":0.1751407895},
{"learn":[9446.207295],"iteration":944,"passed_time":2.956471186,"remaining_time":0.1720697515},
{"learn":[9444.174851],"iteration":945,"passed_time":2.972319682,"remaining_time":0.1696672969},
{"learn":[9429.501837],"iteration":946,"passed_time":2.978717359,"remaining_time":0.1667075185},
{"learn":[9415.358031],"iteration":947,"passed_time":2.984450563,"remaining_time":0.1637040393},
{"learn":[9413.494844],"iteration":948,"passed_time":2.990955156,"remaining_time":0.1607362623},
{"learn":[9411.696884],"iteration":949,"passed_time":2.994712012,"remaining_time":0.1576164217},
{"learn":[9392.882082],"iteration":950,"passed_time":2.999104246,"remaining_time":0.154527979},
{"learn":[9377.355433],"iteration":951,"passed_time":3.003450243,"remaining_time":0.151434466},
{"learn":[9374.691064],"iteration":952,"passed_time":3.007929279,"remaining_time":0.1483448857},
{"learn":[9372.872929],"iteration":953,"passed_time":3.013043831,"remaining_time":0.1452830359},
{"learn":[9363.388969],"iteration":954,"passed_time":3.018083309,"remaining_time":0.1422133496},
{"learn":[9357.046696],"iteration":955,"passed_time":3.022392817,"remaining_time":0.1391059456},
{"learn":[9328.205635],"iteration":956,"passed_time":3.026429606,"remaining_time":0.1359837754},
{"learn":[9316.298207],"iteration":957,"passed_time":3.030795542,"remaining_time":0.1328741261},
{"learn":[9314.290445],"iteration":958,"passed_time":3.035206975,"remaining_time":0.1297638019},
{"learn":[9299.860708],"iteration":959,"passed_time":3.039611218,"remaining_time":0.1266504674},
{"learn":[9296.692898],"iteration":960,"passed_time":3.04243748,"remaining_time":0.1234704076},
{"learn":[9287.528354],"iteration":961,"passed_time":3.0449616,"remaining_time":0.1202791484},
{"learn":[9285.560931],"iteration":962,"passed_time":3.047506544,"remaining_time":0.1170900749},
{"learn":[9281.34541],"iteration":963,"passed_time":3.050590029,"remaining_time":0.1139224492},
{"learn":[9272.467993],"iteration":964,"passed_time":3.053293355,"remaining_time":0.1107412098},
{"learn":[9257.333881],"iteration":965,"passed_time":3.056003718,"remaining_time":0.1075612075},
{"learn":[9256.235436],"iteration":966,"passed_time":3.05925187,"remaining_time":0.1044005292},
{"learn":[9251.357626],"iteration":967,"passed_time":3.063917753,"remaining_time":0.1012865373},
{"learn":[9246.194343],"iteration":968,"passed_time":3.068449572,"remaining_time":0.09816505339},
{"learn":[9243.821451],"iteration":969,"passed_time":3.072433764,"remaining_time":0.09502372465},
{"learn":[9238.055532],"iteration":970,"passed_time":3.076535061,"remaining_time":0.09188415733},
{"learn":[9229.573788],"iteration":971,"passed_time":3.080433209,"remaining_time":0.08873675912},
{"learn":[9224.28465],"iteration":972,"passed_time":3.084415241,"remaining_time":0.08559014545},
{"learn":[9206.624725],"iteration":973,"passed_time":3.088135794,"remaining_time":0.08243483639},
{"learn":[9202.424903],"iteration":974,"passed_time":3.090856868,"remaining_time":0.0792527402},
{"learn":[9199.494136],"iteration":975,"passed_time":3.093564764,"remaining_time":0.0760712647},
{"learn":[9198.283017],"iteration":976,"passed_time":3.09629774,"remaining_time":0.07289134904},
{"learn":[9195.539872],"iteration":977,"passed_time":3.099172673,"remaining_time":0.06971554071},
{"learn":[9193.275621],"iteration":978,"passed_time":3.101864633,"remaining_time":0.06653642217},
{"learn":[9192.15368],"iteration":979,"passed_time":3.104451303,"remaining_time":0.06335614904},
{"learn":[9174.645012],"iteration":980,"passed_time":3.107649446,"remaining_time":0.06018892913},
{"learn":[9163.042264],"iteration":981,"passed_time":3.111901109,"remaining_time":0.05704095718},
{"learn":[9153.835464],"iteration":982,"passed_time":3.115810868,"remaining_time":0.05388482681},
{"learn":[9142.420102],"iteration":983,"passed_time":3.119801753,"remaining_time":0.05072848379},
{"learn":[9127.285717],"iteration":984,"passed_time":3.123953166,"remaining_time":0.04757289085},
{"learn":[9124.831612],"iteration":985,"passed_time":3.127020993,"remaining_time":0.0443998924},
{"learn":[9114.652243],"iteration":986,"passed_time":3.129541746,"remaining_time":0.04121990142},
{"learn":[9112.910363],"iteration":987,"passed_time":3.13230833,"remaining_time":0.03804423073},
{"learn":[9111.912959],"iteration":988,"passed_time":3.13506299,"remaining_time":0.03486925469},
{"learn":[9107.31081],"iteration":989,"passed_time":3.137670738,"remaining_time":0.03169364382},
{"learn":[9101.559159],"iteration":990,"passed_time":3.140123814,"remaining_time":0.02851777429},
{"learn":[9099.326661],"iteration":991,"passed_time":3.14259403,"remaining_time":0.02534350025},
{"learn":[9091.809328],"iteration":992,"passed_time":3.145093848,"remaining_time":0.02217085291},
{"learn":[9077.83371],"iteration":993,"passed_time":3.147586959,"remaining_time":0.01899951887},
{"learn":[9071.321105],"iteration":994,"passed_time":3.150094384,"remaining_time":0.01582962002},
{"learn":[9069.29886],"iteration":995,"passed_time":3.152621365,"remaining_time":0.01266112998},
{"learn":[9061.670061],"iteration":996,"passed_time":3.15572988,"remaining_time":0.009495676671},
{"learn":[9059.176187],"iteration":997,"passed_time":3.16094288,"remaining_time":0.00633455487},
{"learn":[9053.926815],"iteration":998,"passed_time":3.165521271,"remaining_time":0.003168689961},
{"learn":[9040.186655],"iteration":999,"passed_time":3.169693354,"remaining_time":0}
]}